Uart.v
    module uart_interface (
    input i_RW,
    input i_uart_data_ce,
    input i_uart_control_ce, 
    input clk,                  // System clock (44.33 MHz)
    input reset,                // System reset
    input i_UART_TX,            // FT2232 TX line (serial data from host)
    input [7:0] i_control,      // Input to Control register
    input [7:0] i_uart_rxdata,  // Data input from 6809

    output reg o_UART_RX = 1'b1, // FT2232 RX line (serial data to host)
    output reg [7:0] o_uart_txdata, // Data output to 6809
    output reg [7:0] o_uart_status, // UART Status Register
    output reg [7:0] o_control, // output the control register
    output reg o_IRQ = 1'b1      // Active-low interrupt signal to 6809
    );

    // Parameters
    parameter CLOCK_DIVISOR = 4618; // Divisor for 9600 bps with 44.33 MHz clock
    localparam RXIDLE = 1'b0, RECEIVE = 1'b1; // UART RX states
    localparam TXIDLE = 1'b0, TRANSMIT = 1'b1; // UART TX states

    // Internal Signals
    reg [12:0] counter = 0;     // Baud rate counter
    reg baud_clk = 0;           // Baud rate clock
    reg [3:0] rx_bit_counter = 0;  // Bit counter for RX
    reg [3:0] tx_bit_counter = 0;  // Bit counter for TX
    reg [7:0] uart_rx_data = 8'b0; // Data received from FT2232
    reg rx_state = RXIDLE;      // UART RX state
    reg tx_state = TXIDLE;      // UART TX state
    reg irq_flag = 1'b1;        // Internal interrupt flag (active-low)
    reg transmit_flag = 1'b0;
    reg receive_flag = 1'b0;
    reg	[7:0] control_uart = 8'b0;    // bit 0 = Data Ready to Tranmsit, bit 1 =  Enable interrupt
    reg [9:0] uart_tx_data = 10'b0;
    reg [7:0] uart_data_out = 8'b0;

   
   
       
    // Baud Rate Generator
    always @(posedge clk or posedge reset) begin
        if (reset) begin
            counter <= 0;
            baud_clk <= 0;
        end else begin
            if (counter == (CLOCK_DIVISOR - 1)) begin
                counter <= 0;
                baud_clk <= ~baud_clk; // Toggle the baud clock
            end else begin
                counter <= counter + 1;
            end
        end
    end

    // UART RX Process
   always @(posedge baud_clk or posedge reset) begin
      if (reset) begin
         rx_state <= RXIDLE; // default to IDLE state
         rx_bit_counter <= 0; // set counter to zero
         uart_rx_data <= 8'b0; // zero register
         irq_flag <= 1'b1;  // Interrupt inactive on reset
      end else begin
         case (rx_state)
           RXIDLE: begin
              if (!i_UART_TX) begin // Start bit detected (low)
                 rx_state <= RECEIVE; // change to state to receive
                 rx_bit_counter <= 0; // set counter to zero
              end
           end
           RECEIVE: begin
                 uart_rx_data <= {i_UART_TX, uart_rx_data[7:1]}; // shift in the received bit to MSB by concentation TX-->BITS(7-1) makes 8 bits. LSB is dropped with each cycle
                 if (rx_bit_counter == 7) begin
                    rx_state <= RXIDLE;
                    if (control_uart[1]) begin
                       irq_flag <= 1'b0;  // Assert interrupt (active-low)
                    end
                 end
           end
         endcase
      end
   end  
  // UART TX Process
    always @(posedge baud_clk or posedge reset) begin
        if (reset) begin
            tx_state <= TXIDLE;
            tx_bit_counter <= 0;
            o_UART_RX <= 1'b1; // Idle state (high)
	    o_uart_status[1] <= 1'b0; // clear the transmit busy flag
        end else begin
	   case (tx_state)
	     TXIDLE: begin
            if (transmit_flag) begin   
                tx_state <= TRANSMIT;
                o_uart_status[1] <= 1'b1; // Set the transmit busy flag
                tx_bit_counter <= 0;
                uart_tx_data <= {1'b1, uart_data_out, 1'b0}; // Append stop and start bit
            end
	     end
	     TRANSMIT: begin
            o_UART_RX <= uart_tx_data[tx_bit_counter];
            tx_bit_counter <= tx_bit_counter + 1;
            if (tx_bit_counter == 9) begin
                o_uart_status[1] <= 1'b0; // clear the transmit status busy flag
                tx_state <= TXIDLE;
                o_UART_RX <= 1'b1; // Idle line
            end
	     end
	   endcase
        end
    end

    // Assign the IRQ output and control register for UART TX
    always @(posedge clk or posedge reset) begin
        if (reset) begin
            o_IRQ <= 1'b1; // Interrupt inactive (default high)
            transmit_flag <= 1'b0;
            o_uart_status[0] <= 1'b0; // clear rx data ready flag
        end 
        else begin
            if(i_RW && i_uart_control_ce) begin
                o_control <= control_uart;
            end 
            if (!i_RW && i_uart_control_ce) begin
                control_uart <= i_control;
                
            end
            if (!i_RW && i_uart_data_ce && !tx_state) begin
                uart_data_out <= i_uart_rxdata;
                transmit_flag <= 1'b1; // Start transmit for data 
            end
            if (tx_state) begin
                transmit_flag <= 1'b0; // In transmit state, clear the flag
            end
            if (rx_bit_counter == 7 && rx_state == RXIDLE) begin
                o_uart_status[0] <= 1'b1;  // Set RX data ready flag
            end
            if (rx_state == RECEIVE || i_RW && i_uart_data_ce) begin
                o_uart_status[0] <= 1'b0;  // Set RX data ready flag
            end
            if (i_RW && i_uart_data_ce) begin
                o_uart_txdata <= uart_rx_data;  // Set RX data ready flag
            end

            o_IRQ <= irq_flag; // Follow the internal interrupt flag

    end
end




endmodule // uart_interface

TB_Uart.v
`timescale 1ns / 1ns
    module TB_uart;
    reg i_RW;
    reg i_uart_data_ce;
    reg i_uart_control_ce; 
    reg clk;                  // System clock (44.33 MHz)
    reg reset;                // System reset
    reg i_UART_TX;            // FT2232 TX line (serial data from host)
    reg [7:0] i_control;      // reg to Control register
    reg [7:0] i_uart_rxdata;  // Data reg from 6809

    wire o_UART_RX; // FT2232 RX line (serial data to host)
    wire [7:0] o_uart_txdata; // Data output to 6809
    wire [7:0] o_uart_status; // UART Status Register
    wire [7:0] o_control; // output the control register
    wire o_IRQ;      // Active-low interrupt signal to 6809


uart_interface uut(
    .i_RW(i_RW),
    .i_uart_data_ce(i_uart_data_ce),
    .i_uart_control_ce(i_uart_control_ce), 
    .clk(clk),                  // System clock (44.33 MHz)
    .reset(reset),                // System reset
    .i_UART_TX(i_UART_TX),            // FT2232 TX line (serial data from host)
    .i_control(i_control),      // .to Control register
    .i_uart_rxdata(i_uart_rxdata),  // Data .from 6809

    .o_UART_RX(o_UART_RX), // FT2232 RX line (serial data to host)
    .o_uart_txdata(o_uart_txdata), // Data output to 6809
    .o_uart_status(o_uart_status), // UART Status Register
    .o_control(o_control), // output the control register
    .o_IRQ(o_IRQ)      // Active-low interrupt signal to 6809
);

    // Clock generation at 88.67 MHz 
    localparam CLOCK_PERIOD_NS = 11.285; // 88.67 MHz 
    initial clk = 0;
    always #(CLOCK_PERIOD_NS / 2) clk = ~clk;

    initial begin
        $dumpfile("simulation.vcd");
        $dumpvars(0, TB_uart);

        // Initialize Inputs
        i_RW = 0;
        i_uart_data_ce = 0;
        i_uart_control_ce = 0;
        reset = 1;
        #10;
        reset = 0;
      #100000;
 


        $display("Final Data Received: %h", o_uart_txdata);
        $finish;
    end





























endmodule

simulation.vcd
$date
	Fri Feb  7 21:37:58 2025
$end
$version
	Icarus Verilog
$end
$timescale
	1ns
$end
$scope module TB_uart $end
$var wire 8 ! o_uart_txdata [7:0] $end
$var wire 8 " o_uart_status [7:0] $end
$var wire 8 # o_control [7:0] $end
$var wire 1 $ o_UART_RX $end
$var wire 1 % o_IRQ $end
$var reg 1 & clk $end
$var reg 1 ' i_RW $end
$var reg 1 ( i_UART_TX $end
$var reg 8 ) i_control [7:0] $end
$var reg 1 * i_uart_control_ce $end
$var reg 1 + i_uart_data_ce $end
$var reg 8 , i_uart_rxdata [7:0] $end
$var reg 1 - reset $end
$scope module uut $end
$var wire 1 & clk $end
$var wire 1 ' i_RW $end
$var wire 1 ( i_UART_TX $end
$var wire 8 . i_control [7:0] $end
$var wire 1 * i_uart_control_ce $end
$var wire 1 + i_uart_data_ce $end
$var wire 8 / i_uart_rxdata [7:0] $end
$var wire 1 - reset $end
$var reg 1 0 baud_clk $end
$var reg 8 1 control_uart [7:0] $end
$var reg 13 2 counter [12:0] $end
$var reg 1 3 irq_flag $end
$var reg 1 % o_IRQ $end
$var reg 1 $ o_UART_RX $end
$var reg 8 4 o_control [7:0] $end
$var reg 8 5 o_uart_status [7:0] $end
$var reg 8 6 o_uart_txdata [7:0] $end
$var reg 1 7 receive_flag $end
$var reg 4 8 rx_bit_counter [3:0] $end
$var reg 1 9 rx_state $end
$var reg 1 : transmit_flag $end
$var reg 4 ; tx_bit_counter [3:0] $end
$var reg 1 < tx_state $end
$var reg 8 = uart_data_out [7:0] $end
$var reg 8 > uart_rx_data [7:0] $end
$var reg 10 ? uart_tx_data [9:0] $end
$upscope $end
$upscope $end
$enddefinitions $end
#0
$dumpvars
b0 ?
b0 >
b0 =
0<
b0 ;
0:
09
b0 8
07
bx 6
bx00 5
bx 4
13
b0 2
b0 1
00
bx /
bx .
1-
bx ,
0+
0*
bx )
x(
0'
0&
1%
1$
bx #
bx00 "
bx !
$end
#6
1&
#10
0-
#12
0&
#18
b1 2
1&
#24
0&
#30
b10 2
1&
#36
0&
#42
b11 2
1&
#48
0&
#54
b100 2
1&
#60
0&
#66
b101 2
1&
#72
0&
#78
b110 2
1&
#84
0&
#90
b111 2
1&
#96
0&
#102
b1000 2
1&
#108
0&
#114
b1001 2
1&
#120
0&
#126
b1010 2
1&
#132
0&
#138
b1011 2
1&
#144
0&
#150
b1100 2
1&
#156
0&
#162
b1101 2
1&
#168
0&
#174
b1110 2
1&
#180
0&
#186
b1111 2
1&
#192
0&
#198
b10000 2
1&
#204
0&
#210
b10001 2
1&
#216
0&
#222
b10010 2
1&
#228
0&
#234
b10011 2
1&
#240
0&
#246
b10100 2
1&
#252
0&
#258
b10101 2
1&
#264
0&
#270
b10110 2
1&
#276
0&
#282
b10111 2
1&
#288
0&
#294
b11000 2
1&
#300
0&
#306
b11001 2
1&
#312
0&
#318
b11010 2
1&
#324
0&
#330
b11011 2
1&
#336
0&
#342
b11100 2
1&
#348
0&
#354
b11101 2
1&
#360
0&
#366
b11110 2
1&
#372
0&
#378
b11111 2
1&
#384
0&
#390
b100000 2
1&
#396
0&
#402
b100001 2
1&
#408
0&
#414
b100010 2
1&
#420
0&
#426
b100011 2
1&
#432
0&
#438
b100100 2
1&
#444
0&
#450
b100101 2
1&
#456
0&
#462
b100110 2
1&
#468
0&
#474
b100111 2
1&
#480
0&
#486
b101000 2
1&
#492
0&
#498
b101001 2
1&
#504
0&
#510
b101010 2
1&
#516
0&
#522
b101011 2
1&
#528
0&
#534
b101100 2
1&
#540
0&
#546
b101101 2
1&
#552
0&
#558
b101110 2
1&
#564
0&
#570
b101111 2
1&
#576
0&
#582
b110000 2
1&
#588
0&
#594
b110001 2
1&
#600
0&
#606
b110010 2
1&
#612
0&
#618
b110011 2
1&
#624
0&
#630
b110100 2
1&
#636
0&
#642
b110101 2
1&
#648
0&
#654
b110110 2
1&
#660
0&
#666
b110111 2
1&
#672
0&
#678
b111000 2
1&
#684
0&
#690
b111001 2
1&
#696
0&
#702
b111010 2
1&
#708
0&
#714
b111011 2
1&
#720
0&
#726
b111100 2
1&
#732
0&
#738
b111101 2
1&
#744
0&
#750
b111110 2
1&
#756
0&
#762
b111111 2
1&
#768
0&
#774
b1000000 2
1&
#780
0&
#786
b1000001 2
1&
#792
0&
#798
b1000010 2
1&
#804
0&
#810
b1000011 2
1&
#816
0&
#822
b1000100 2
1&
#828
0&
#834
b1000101 2
1&
#840
0&
#846
b1000110 2
1&
#852
0&
#858
b1000111 2
1&
#864
0&
#870
b1001000 2
1&
#876
0&
#882
b1001001 2
1&
#888
0&
#894
b1001010 2
1&
#900
0&
#906
b1001011 2
1&
#912
0&
#918
b1001100 2
1&
#924
0&
#930
b1001101 2
1&
#936
0&
#942
b1001110 2
1&
#948
0&
#954
b1001111 2
1&
#960
0&
#966
b1010000 2
1&
#972
0&
#978
b1010001 2
1&
#984
0&
#990
b1010010 2
1&
#996
0&
#1002
b1010011 2
1&
#1008
0&
#1014
b1010100 2
1&
#1020
0&
#1026
b1010101 2
1&
#1032
0&
#1038
b1010110 2
1&
#1044
0&
#1050
b1010111 2
1&
#1056
0&
#1062
b1011000 2
1&
#1068
0&
#1074
b1011001 2
1&
#1080
0&
#1086
b1011010 2
1&
#1092
0&
#1098
b1011011 2
1&
#1104
0&
#1110
b1011100 2
1&
#1116
0&
#1122
b1011101 2
1&
#1128
0&
#1134
b1011110 2
1&
#1140
0&
#1146
b1011111 2
1&
#1152
0&
#1158
b1100000 2
1&
#1164
0&
#1170
b1100001 2
1&
#1176
0&
#1182
b1100010 2
1&
#1188
0&
#1194
b1100011 2
1&
#1200
0&
#1206
b1100100 2
1&
#1212
0&
#1218
b1100101 2
1&
#1224
0&
#1230
b1100110 2
1&
#1236
0&
#1242
b1100111 2
1&
#1248
0&
#1254
b1101000 2
1&
#1260
0&
#1266
b1101001 2
1&
#1272
0&
#1278
b1101010 2
1&
#1284
0&
#1290
b1101011 2
1&
#1296
0&
#1302
b1101100 2
1&
#1308
0&
#1314
b1101101 2
1&
#1320
0&
#1326
b1101110 2
1&
#1332
0&
#1338
b1101111 2
1&
#1344
0&
#1350
b1110000 2
1&
#1356
0&
#1362
b1110001 2
1&
#1368
0&
#1374
b1110010 2
1&
#1380
0&
#1386
b1110011 2
1&
#1392
0&
#1398
b1110100 2
1&
#1404
0&
#1410
b1110101 2
1&
#1416
0&
#1422
b1110110 2
1&
#1428
0&
#1434
b1110111 2
1&
#1440
0&
#1446
b1111000 2
1&
#1452
0&
#1458
b1111001 2
1&
#1464
0&
#1470
b1111010 2
1&
#1476
0&
#1482
b1111011 2
1&
#1488
0&
#1494
b1111100 2
1&
#1500
0&
#1506
b1111101 2
1&
#1512
0&
#1518
b1111110 2
1&
#1524
0&
#1530
b1111111 2
1&
#1536
0&
#1542
b10000000 2
1&
#1548
0&
#1554
b10000001 2
1&
#1560
0&
#1566
b10000010 2
1&
#1572
0&
#1578
b10000011 2
1&
#1584
0&
#1590
b10000100 2
1&
#1596
0&
#1602
b10000101 2
1&
#1608
0&
#1614
b10000110 2
1&
#1620
0&
#1626
b10000111 2
1&
#1632
0&
#1638
b10001000 2
1&
#1644
0&
#1650
b10001001 2
1&
#1656
0&
#1662
b10001010 2
1&
#1668
0&
#1674
b10001011 2
1&
#1680
0&
#1686
b10001100 2
1&
#1692
0&
#1698
b10001101 2
1&
#1704
0&
#1710
b10001110 2
1&
#1716
0&
#1722
b10001111 2
1&
#1728
0&
#1734
b10010000 2
1&
#1740
0&
#1746
b10010001 2
1&
#1752
0&
#1758
b10010010 2
1&
#1764
0&
#1770
b10010011 2
1&
#1776
0&
#1782
b10010100 2
1&
#1788
0&
#1794
b10010101 2
1&
#1800
0&
#1806
b10010110 2
1&
#1812
0&
#1818
b10010111 2
1&
#1824
0&
#1830
b10011000 2
1&
#1836
0&
#1842
b10011001 2
1&
#1848
0&
#1854
b10011010 2
1&
#1860
0&
#1866
b10011011 2
1&
#1872
0&
#1878
b10011100 2
1&
#1884
0&
#1890
b10011101 2
1&
#1896
0&
#1902
b10011110 2
1&
#1908
0&
#1914
b10011111 2
1&
#1920
0&
#1926
b10100000 2
1&
#1932
0&
#1938
b10100001 2
1&
#1944
0&
#1950
b10100010 2
1&
#1956
0&
#1962
b10100011 2
1&
#1968
0&
#1974
b10100100 2
1&
#1980
0&
#1986
b10100101 2
1&
#1992
0&
#1998
b10100110 2
1&
#2004
0&
#2010
b10100111 2
1&
#2016
0&
#2022
b10101000 2
1&
#2028
0&
#2034
b10101001 2
1&
#2040
0&
#2046
b10101010 2
1&
#2052
0&
#2058
b10101011 2
1&
#2064
0&
#2070
b10101100 2
1&
#2076
0&
#2082
b10101101 2
1&
#2088
0&
#2094
b10101110 2
1&
#2100
0&
#2106
b10101111 2
1&
#2112
0&
#2118
b10110000 2
1&
#2124
0&
#2130
b10110001 2
1&
#2136
0&
#2142
b10110010 2
1&
#2148
0&
#2154
b10110011 2
1&
#2160
0&
#2166
b10110100 2
1&
#2172
0&
#2178
b10110101 2
1&
#2184
0&
#2190
b10110110 2
1&
#2196
0&
#2202
b10110111 2
1&
#2208
0&
#2214
b10111000 2
1&
#2220
0&
#2226
b10111001 2
1&
#2232
0&
#2238
b10111010 2
1&
#2244
0&
#2250
b10111011 2
1&
#2256
0&
#2262
b10111100 2
1&
#2268
0&
#2274
b10111101 2
1&
#2280
0&
#2286
b10111110 2
1&
#2292
0&
#2298
b10111111 2
1&
#2304
0&
#2310
b11000000 2
1&
#2316
0&
#2322
b11000001 2
1&
#2328
0&
#2334
b11000010 2
1&
#2340
0&
#2346
b11000011 2
1&
#2352
0&
#2358
b11000100 2
1&
#2364
0&
#2370
b11000101 2
1&
#2376
0&
#2382
b11000110 2
1&
#2388
0&
#2394
b11000111 2
1&
#2400
0&
#2406
b11001000 2
1&
#2412
0&
#2418
b11001001 2
1&
#2424
0&
#2430
b11001010 2
1&
#2436
0&
#2442
b11001011 2
1&
#2448
0&
#2454
b11001100 2
1&
#2460
0&
#2466
b11001101 2
1&
#2472
0&
#2478
b11001110 2
1&
#2484
0&
#2490
b11001111 2
1&
#2496
0&
#2502
b11010000 2
1&
#2508
0&
#2514
b11010001 2
1&
#2520
0&
#2526
b11010010 2
1&
#2532
0&
#2538
b11010011 2
1&
#2544
0&
#2550
b11010100 2
1&
#2556
0&
#2562
b11010101 2
1&
#2568
0&
#2574
b11010110 2
1&
#2580
0&
#2586
b11010111 2
1&
#2592
0&
#2598
b11011000 2
1&
#2604
0&
#2610
b11011001 2
1&
#2616
0&
#2622
b11011010 2
1&
#2628
0&
#2634
b11011011 2
1&
#2640
0&
#2646
b11011100 2
1&
#2652
0&
#2658
b11011101 2
1&
#2664
0&
#2670
b11011110 2
1&
#2676
0&
#2682
b11011111 2
1&
#2688
0&
#2694
b11100000 2
1&
#2700
0&
#2706
b11100001 2
1&
#2712
0&
#2718
b11100010 2
1&
#2724
0&
#2730
b11100011 2
1&
#2736
0&
#2742
b11100100 2
1&
#2748
0&
#2754
b11100101 2
1&
#2760
0&
#2766
b11100110 2
1&
#2772
0&
#2778
b11100111 2
1&
#2784
0&
#2790
b11101000 2
1&
#2796
0&
#2802
b11101001 2
1&
#2808
0&
#2814
b11101010 2
1&
#2820
0&
#2826
b11101011 2
1&
#2832
0&
#2838
b11101100 2
1&
#2844
0&
#2850
b11101101 2
1&
#2856
0&
#2862
b11101110 2
1&
#2868
0&
#2874
b11101111 2
1&
#2880
0&
#2886
b11110000 2
1&
#2892
0&
#2898
b11110001 2
1&
#2904
0&
#2910
b11110010 2
1&
#2916
0&
#2922
b11110011 2
1&
#2928
0&
#2934
b11110100 2
1&
#2940
0&
#2946
b11110101 2
1&
#2952
0&
#2958
b11110110 2
1&
#2964
0&
#2970
b11110111 2
1&
#2976
0&
#2982
b11111000 2
1&
#2988
0&
#2994
b11111001 2
1&
#3000
0&
#3006
b11111010 2
1&
#3012
0&
#3018
b11111011 2
1&
#3024
0&
#3030
b11111100 2
1&
#3036
0&
#3042
b11111101 2
1&
#3048
0&
#3054
b11111110 2
1&
#3060
0&
#3066
b11111111 2
1&
#3072
0&
#3078
b100000000 2
1&
#3084
0&
#3090
b100000001 2
1&
#3096
0&
#3102
b100000010 2
1&
#3108
0&
#3114
b100000011 2
1&
#3120
0&
#3126
b100000100 2
1&
#3132
0&
#3138
b100000101 2
1&
#3144
0&
#3150
b100000110 2
1&
#3156
0&
#3162
b100000111 2
1&
#3168
0&
#3174
b100001000 2
1&
#3180
0&
#3186
b100001001 2
1&
#3192
0&
#3198
b100001010 2
1&
#3204
0&
#3210
b100001011 2
1&
#3216
0&
#3222
b100001100 2
1&
#3228
0&
#3234
b100001101 2
1&
#3240
0&
#3246
b100001110 2
1&
#3252
0&
#3258
b100001111 2
1&
#3264
0&
#3270
b100010000 2
1&
#3276
0&
#3282
b100010001 2
1&
#3288
0&
#3294
b100010010 2
1&
#3300
0&
#3306
b100010011 2
1&
#3312
0&
#3318
b100010100 2
1&
#3324
0&
#3330
b100010101 2
1&
#3336
0&
#3342
b100010110 2
1&
#3348
0&
#3354
b100010111 2
1&
#3360
0&
#3366
b100011000 2
1&
#3372
0&
#3378
b100011001 2
1&
#3384
0&
#3390
b100011010 2
1&
#3396
0&
#3402
b100011011 2
1&
#3408
0&
#3414
b100011100 2
1&
#3420
0&
#3426
b100011101 2
1&
#3432
0&
#3438
b100011110 2
1&
#3444
0&
#3450
b100011111 2
1&
#3456
0&
#3462
b100100000 2
1&
#3468
0&
#3474
b100100001 2
1&
#3480
0&
#3486
b100100010 2
1&
#3492
0&
#3498
b100100011 2
1&
#3504
0&
#3510
b100100100 2
1&
#3516
0&
#3522
b100100101 2
1&
#3528
0&
#3534
b100100110 2
1&
#3540
0&
#3546
b100100111 2
1&
#3552
0&
#3558
b100101000 2
1&
#3564
0&
#3570
b100101001 2
1&
#3576
0&
#3582
b100101010 2
1&
#3588
0&
#3594
b100101011 2
1&
#3600
0&
#3606
b100101100 2
1&
#3612
0&
#3618
b100101101 2
1&
#3624
0&
#3630
b100101110 2
1&
#3636
0&
#3642
b100101111 2
1&
#3648
0&
#3654
b100110000 2
1&
#3660
0&
#3666
b100110001 2
1&
#3672
0&
#3678
b100110010 2
1&
#3684
0&
#3690
b100110011 2
1&
#3696
0&
#3702
b100110100 2
1&
#3708
0&
#3714
b100110101 2
1&
#3720
0&
#3726
b100110110 2
1&
#3732
0&
#3738
b100110111 2
1&
#3744
0&
#3750
b100111000 2
1&
#3756
0&
#3762
b100111001 2
1&
#3768
0&
#3774
b100111010 2
1&
#3780
0&
#3786
b100111011 2
1&
#3792
0&
#3798
b100111100 2
1&
#3804
0&
#3810
b100111101 2
1&
#3816
0&
#3822
b100111110 2
1&
#3828
0&
#3834
b100111111 2
1&
#3840
0&
#3846
b101000000 2
1&
#3852
0&
#3858
b101000001 2
1&
#3864
0&
#3870
b101000010 2
1&
#3876
0&
#3882
b101000011 2
1&
#3888
0&
#3894
b101000100 2
1&
#3900
0&
#3906
b101000101 2
1&
#3912
0&
#3918
b101000110 2
1&
#3924
0&
#3930
b101000111 2
1&
#3936
0&
#3942
b101001000 2
1&
#3948
0&
#3954
b101001001 2
1&
#3960
0&
#3966
b101001010 2
1&
#3972
0&
#3978
b101001011 2
1&
#3984
0&
#3990
b101001100 2
1&
#3996
0&
#4002
b101001101 2
1&
#4008
0&
#4014
b101001110 2
1&
#4020
0&
#4026
b101001111 2
1&
#4032
0&
#4038
b101010000 2
1&
#4044
0&
#4050
b101010001 2
1&
#4056
0&
#4062
b101010010 2
1&
#4068
0&
#4074
b101010011 2
1&
#4080
0&
#4086
b101010100 2
1&
#4092
0&
#4098
b101010101 2
1&
#4104
0&
#4110
b101010110 2
1&
#4116
0&
#4122
b101010111 2
1&
#4128
0&
#4134
b101011000 2
1&
#4140
0&
#4146
b101011001 2
1&
#4152
0&
#4158
b101011010 2
1&
#4164
0&
#4170
b101011011 2
1&
#4176
0&
#4182
b101011100 2
1&
#4188
0&
#4194
b101011101 2
1&
#4200
0&
#4206
b101011110 2
1&
#4212
0&
#4218
b101011111 2
1&
#4224
0&
#4230
b101100000 2
1&
#4236
0&
#4242
b101100001 2
1&
#4248
0&
#4254
b101100010 2
1&
#4260
0&
#4266
b101100011 2
1&
#4272
0&
#4278
b101100100 2
1&
#4284
0&
#4290
b101100101 2
1&
#4296
0&
#4302
b101100110 2
1&
#4308
0&
#4314
b101100111 2
1&
#4320
0&
#4326
b101101000 2
1&
#4332
0&
#4338
b101101001 2
1&
#4344
0&
#4350
b101101010 2
1&
#4356
0&
#4362
b101101011 2
1&
#4368
0&
#4374
b101101100 2
1&
#4380
0&
#4386
b101101101 2
1&
#4392
0&
#4398
b101101110 2
1&
#4404
0&
#4410
b101101111 2
1&
#4416
0&
#4422
b101110000 2
1&
#4428
0&
#4434
b101110001 2
1&
#4440
0&
#4446
b101110010 2
1&
#4452
0&
#4458
b101110011 2
1&
#4464
0&
#4470
b101110100 2
1&
#4476
0&
#4482
b101110101 2
1&
#4488
0&
#4494
b101110110 2
1&
#4500
0&
#4506
b101110111 2
1&
#4512
0&
#4518
b101111000 2
1&
#4524
0&
#4530
b101111001 2
1&
#4536
0&
#4542
b101111010 2
1&
#4548
0&
#4554
b101111011 2
1&
#4560
0&
#4566
b101111100 2
1&
#4572
0&
#4578
b101111101 2
1&
#4584
0&
#4590
b101111110 2
1&
#4596
0&
#4602
b101111111 2
1&
#4608
0&
#4614
b110000000 2
1&
#4620
0&
#4626
b110000001 2
1&
#4632
0&
#4638
b110000010 2
1&
#4644
0&
#4650
b110000011 2
1&
#4656
0&
#4662
b110000100 2
1&
#4668
0&
#4674
b110000101 2
1&
#4680
0&
#4686
b110000110 2
1&
#4692
0&
#4698
b110000111 2
1&
#4704
0&
#4710
b110001000 2
1&
#4716
0&
#4722
b110001001 2
1&
#4728
0&
#4734
b110001010 2
1&
#4740
0&
#4746
b110001011 2
1&
#4752
0&
#4758
b110001100 2
1&
#4764
0&
#4770
b110001101 2
1&
#4776
0&
#4782
b110001110 2
1&
#4788
0&
#4794
b110001111 2
1&
#4800
0&
#4806
b110010000 2
1&
#4812
0&
#4818
b110010001 2
1&
#4824
0&
#4830
b110010010 2
1&
#4836
0&
#4842
b110010011 2
1&
#4848
0&
#4854
b110010100 2
1&
#4860
0&
#4866
b110010101 2
1&
#4872
0&
#4878
b110010110 2
1&
#4884
0&
#4890
b110010111 2
1&
#4896
0&
#4902
b110011000 2
1&
#4908
0&
#4914
b110011001 2
1&
#4920
0&
#4926
b110011010 2
1&
#4932
0&
#4938
b110011011 2
1&
#4944
0&
#4950
b110011100 2
1&
#4956
0&
#4962
b110011101 2
1&
#4968
0&
#4974
b110011110 2
1&
#4980
0&
#4986
b110011111 2
1&
#4992
0&
#4998
b110100000 2
1&
#5004
0&
#5010
b110100001 2
1&
#5016
0&
#5022
b110100010 2
1&
#5028
0&
#5034
b110100011 2
1&
#5040
0&
#5046
b110100100 2
1&
#5052
0&
#5058
b110100101 2
1&
#5064
0&
#5070
b110100110 2
1&
#5076
0&
#5082
b110100111 2
1&
#5088
0&
#5094
b110101000 2
1&
#5100
0&
#5106
b110101001 2
1&
#5112
0&
#5118
b110101010 2
1&
#5124
0&
#5130
b110101011 2
1&
#5136
0&
#5142
b110101100 2
1&
#5148
0&
#5154
b110101101 2
1&
#5160
0&
#5166
b110101110 2
1&
#5172
0&
#5178
b110101111 2
1&
#5184
0&
#5190
b110110000 2
1&
#5196
0&
#5202
b110110001 2
1&
#5208
0&
#5214
b110110010 2
1&
#5220
0&
#5226
b110110011 2
1&
#5232
0&
#5238
b110110100 2
1&
#5244
0&
#5250
b110110101 2
1&
#5256
0&
#5262
b110110110 2
1&
#5268
0&
#5274
b110110111 2
1&
#5280
0&
#5286
b110111000 2
1&
#5292
0&
#5298
b110111001 2
1&
#5304
0&
#5310
b110111010 2
1&
#5316
0&
#5322
b110111011 2
1&
#5328
0&
#5334
b110111100 2
1&
#5340
0&
#5346
b110111101 2
1&
#5352
0&
#5358
b110111110 2
1&
#5364
0&
#5370
b110111111 2
1&
#5376
0&
#5382
b111000000 2
1&
#5388
0&
#5394
b111000001 2
1&
#5400
0&
#5406
b111000010 2
1&
#5412
0&
#5418
b111000011 2
1&
#5424
0&
#5430
b111000100 2
1&
#5436
0&
#5442
b111000101 2
1&
#5448
0&
#5454
b111000110 2
1&
#5460
0&
#5466
b111000111 2
1&
#5472
0&
#5478
b111001000 2
1&
#5484
0&
#5490
b111001001 2
1&
#5496
0&
#5502
b111001010 2
1&
#5508
0&
#5514
b111001011 2
1&
#5520
0&
#5526
b111001100 2
1&
#5532
0&
#5538
b111001101 2
1&
#5544
0&
#5550
b111001110 2
1&
#5556
0&
#5562
b111001111 2
1&
#5568
0&
#5574
b111010000 2
1&
#5580
0&
#5586
b111010001 2
1&
#5592
0&
#5598
b111010010 2
1&
#5604
0&
#5610
b111010011 2
1&
#5616
0&
#5622
b111010100 2
1&
#5628
0&
#5634
b111010101 2
1&
#5640
0&
#5646
b111010110 2
1&
#5652
0&
#5658
b111010111 2
1&
#5664
0&
#5670
b111011000 2
1&
#5676
0&
#5682
b111011001 2
1&
#5688
0&
#5694
b111011010 2
1&
#5700
0&
#5706
b111011011 2
1&
#5712
0&
#5718
b111011100 2
1&
#5724
0&
#5730
b111011101 2
1&
#5736
0&
#5742
b111011110 2
1&
#5748
0&
#5754
b111011111 2
1&
#5760
0&
#5766
b111100000 2
1&
#5772
0&
#5778
b111100001 2
1&
#5784
0&
#5790
b111100010 2
1&
#5796
0&
#5802
b111100011 2
1&
#5808
0&
#5814
b111100100 2
1&
#5820
0&
#5826
b111100101 2
1&
#5832
0&
#5838
b111100110 2
1&
#5844
0&
#5850
b111100111 2
1&
#5856
0&
#5862
b111101000 2
1&
#5868
0&
#5874
b111101001 2
1&
#5880
0&
#5886
b111101010 2
1&
#5892
0&
#5898
b111101011 2
1&
#5904
0&
#5910
b111101100 2
1&
#5916
0&
#5922
b111101101 2
1&
#5928
0&
#5934
b111101110 2
1&
#5940
0&
#5946
b111101111 2
1&
#5952
0&
#5958
b111110000 2
1&
#5964
0&
#5970
b111110001 2
1&
#5976
0&
#5982
b111110010 2
1&
#5988
0&
#5994
b111110011 2
1&
#6000
0&
#6006
b111110100 2
1&
#6012
0&
#6018
b111110101 2
1&
#6024
0&
#6030
b111110110 2
1&
#6036
0&
#6042
b111110111 2
1&
#6048
0&
#6054
b111111000 2
1&
#6060
0&
#6066
b111111001 2
1&
#6072
0&
#6078
b111111010 2
1&
#6084
0&
#6090
b111111011 2
1&
#6096
0&
#6102
b111111100 2
1&
#6108
0&
#6114
b111111101 2
1&
#6120
0&
#6126
b111111110 2
1&
#6132
0&
#6138
b111111111 2
1&
#6144
0&
#6150
b1000000000 2
1&
#6156
0&
#6162
b1000000001 2
1&
#6168
0&
#6174
b1000000010 2
1&
#6180
0&
#6186
b1000000011 2
1&
#6192
0&
#6198
b1000000100 2
1&
#6204
0&
#6210
b1000000101 2
1&
#6216
0&
#6222
b1000000110 2
1&
#6228
0&
#6234
b1000000111 2
1&
#6240
0&
#6246
b1000001000 2
1&
#6252
0&
#6258
b1000001001 2
1&
