FlashSpi.v
// SPI device uses SPI Mode 0, with active low Chip Select
module spi_flash_controller (
    input spi_ce,            // SPI chip select signal from address decoder
    input reset,             // Reset signal
    input [15:0] i_ADDRESS_BUS, // Address from 6809 (16 bits)
    input [7:0] i_DataBus,  // Data input from 6809
    input i_RW,               // Read/Write control signal (only reads for flash)
    input clk,                // System clock
    input i_SPI_MISO,         // SPI Master In Slave Out
    output reg o_SPI_CLK,     // SPI Clock
    output reg o_SPI_MOSI,    // SPI Master Out Slave In
    output reg o_SPI_CS,      // SPI Chip Select (active low)
    output reg [7:0] o_spi_data,  // Data output to 6809
    output reg o_MemoryReady
);

    wire [7:0] spi_read_command = 8'h03; // Command for SPI flash (READ command is 0x03)
    wire [7:0] spi_write_command = 8'h02; // Command for SPI flash (WRITE command is 0x02)
    reg [23:0] spi_address = 24'b0; // Address for SPI flash (24 bits)
    reg [5:0] bit_counter = 6'd0;     // Tracks SPI transaction progress (6 bits to cover up to 40)
    reg spi_read_active = 0;               // Indicates SPI operation is active
    reg spi_write_active = 0;               // Indicates SPI operation is active
    reg clock_delay = 0;
    reg [7:0] spi_datawrite = 8'b0;          // Data to write to SPI flash


    always @(posedge clk) begin
        if (~reset) begin
            o_spi_data <= 8'b0;          // Reset data
            bit_counter <= 6'b0;       // Reset bit counter
            spi_read_active <= 1'b0;        // Reset SPI read active flag
            spi_write_active <= 1'b0;        // Reset SPI write active flag
            o_SPI_CLK = 1'b0;         // Reset SPI 
            o_MemoryReady <= 1'b1;    // Allow the 6809 to continue
        end

        // Start SPI transaction when chip select is active and it's a read cycle
        if (spi_ce && i_RW && !spi_read_active && !spi_write_active && reset) begin
            spi_address <= {12'b0, i_ADDRESS_BUS[11:0]}; // Lower 12 bits of address to 24-bit SPI address
            spi_read_active <= 1'b1;         // Mark SPI as active
            bit_counter <= 6'd0;        // Reset bit counter
            clock_delay <= 1'b0;
       end
       else if (spi_ce && ~i_RW && !spi_write_active && !spi_read_active && reset) begin
            spi_address <= {12'b0, i_ADDRESS_BUS[11:0]}; // Lower 12 bits of address to 24-bit SPI address
            spi_write_active <= 1'b1;         // Mark SPI as active
            bit_counter <= 6'd0;        // Reset bit counter
            clock_delay <= 1'b0;
            spi_datawrite <= i_DataBus;
        end

        
        // Read data from SPI flash
        if (spi_read_active && reset) begin
            o_SPI_CS <= 1'b0;           // Activate SPI chip select
            o_MemoryReady <= 1'b0;     // Keep 6809 in wait state during SPI transaction

            if (clock_delay) begin 
                o_SPI_CLK = ~o_SPI_CLK;   // Toggle SPI clock
            end
            clock_delay <= 1'b1;

            if (~o_SPI_CLK) begin
                // On rising edge of SPI clock, handle data transfer
                if (bit_counter < 6'd8) begin //7
                    // Send SPI command (8 bits)
                    o_SPI_MOSI <= spi_read_command[7 - bit_counter];
                end else if (bit_counter < 6'd32) begin
                    // Send 24-bit SPI address (address starts at bit 8)
                    o_SPI_MOSI <= spi_address[31 - bit_counter];
                end else if (bit_counter == 6'd40) begin
                    // End of SPI transaction
                    spi_read_active <= 1'b0;      // Mark SPI as inactive
                    o_MemoryReady <= 1'b1;     // Allow the 6809 to continue
                end
            end
            else begin
                if (bit_counter < 6'd40) begin
                    // Receive 8-bit data (after address)
                    o_spi_data[7 - (bit_counter - 6'd32)] <= i_SPI_MISO;
                end
                // Increment bit counter (always within 6-bit range, safe to truncate)
                bit_counter <= bit_counter + 1;
            end
        end 
        // Write data to SPI flash
        else if (spi_write_active && reset) begin
            o_SPI_CS <= 1'b0;           // Activate SPI chip select
            o_MemoryReady <= 1'b0;     // Keep 6809 in wait state during SPI transaction

            if (clock_delay) begin 
                o_SPI_CLK = ~o_SPI_CLK;   // Toggle SPI clock
            end
            clock_delay <= 1'b1;

            if (~o_SPI_CLK) begin
                // On rising edge of SPI clock, handle data transfer
                if (bit_counter < 6'd8) begin //7
                    // Send SPI command (8 bits)
                    o_SPI_MOSI <= spi_write_command[7 - bit_counter];
                end else if (bit_counter < 6'd32) begin
                    // Send 24-bit SPI address (address starts at bit 8)
                    o_SPI_MOSI <= spi_address[31 - bit_counter];
                end
                else if (bit_counter < 6'd40) begin
                // Receive 8-bit data (after address)
                o_SPI_MOSI <= spi_datawrite[7 - (bit_counter - 6'd32)];
                end    
                else if (bit_counter == 6'd40) begin
                    // End of SPI transaction
                    spi_write_active <= 1'b0;      // Mark SPI as inactive
                    o_MemoryReady <= 1'b1;     // Allow the 6809 to continue
                end
            end
            else begin
                // Increment bit counter (always within 6-bit range, safe to truncate)
                bit_counter <= bit_counter + 1;
            end
        end else begin
            // Idle state: set SPI signals to default
            o_SPI_MOSI <= 1'bz;        // High Impedance at idle
            o_SPI_CLK <= 1'b0;         // Clock low in idle (for SPI Mode 0)
            o_MemoryReady <= 1'b1;     // Allow the 6809 to continue
            o_SPI_CS <= 1'b1;        // Deactivate SPI chip select
        end
    end
endmodule

TB_FlashSpi.v
`timescale 1ns / 1ns
module tb_spi_flash_controller;

    reg spi_ce;
    reg reset;
    reg [15:0] i_ADDRESS_BUS;
    reg [7:0] i_DataBus;
    reg i_RW;
    reg clk;
    reg i_SPI_MISO;
    wire o_SPI_CLK;
    wire o_SPI_MOSI;
    wire o_SPI_CS;
    wire [7:0] o_DATA;
    wire o_MemoryReady;

    // Instantiate the Unit Under Test (UUT)
    spi_flash_controller uut (
        .spi_ce(spi_ce),
        .reset(reset),
        .i_ADDRESS_BUS(i_ADDRESS_BUS),
        .i_DataBus(i_DataBus),
        .i_RW(i_RW),
        .clk(clk),
        .i_SPI_MISO(i_SPI_MISO),
        .o_SPI_CLK(o_SPI_CLK),
        .o_SPI_MOSI(o_SPI_MOSI),
        .o_SPI_CS(o_SPI_CS),
        .o_spi_data(o_DATA),
        .o_MemoryReady(o_MemoryReady)
    );

    // Clock generation at 88.67 MHz 
    localparam CLOCK_PERIOD_NS = 11.285; // 88.67 MHz 
    initial clk = 0;
    always #(CLOCK_PERIOD_NS / 2) clk = ~clk;

    // Simulation task for SPI flash read operation
    task spi_flash_read(input [15:0] address);
        begin
            reset = 1;
            #10;
            reset = 0;
            #10;
            reset = 1;
            #24;
            spi_ce = 1;
            i_ADDRESS_BUS = address;
            #774;  // Wait for SPI operation to begin
            #24 i_SPI_MISO = 1;
            #24 i_SPI_MISO = 1;
            #24 i_SPI_MISO = 1;
            #24 i_SPI_MISO = 1;
            #24 i_SPI_MISO = 1;
            #24 i_SPI_MISO = 0;
            #24 i_SPI_MISO = 1;
            #24 i_SPI_MISO = 0;
            spi_ce = 0;
            i_RW = 1;
            #100;  // Return to idle state after operation
        end
    endtask
    // Simulation task for SPI flash read operation
    task spi_flash_write(input [15:0] address, input [7:0] databus);
        begin


            #24;
            #24;
            #24;
            i_RW = 0;
            spi_ce = 1;
            i_ADDRESS_BUS = address;
            i_DataBus = databus;
            #966;  // Wait for SPI operation to begin

            spi_ce = 0;
            i_RW = 1;
            #100;  // Return to idle state after operation
        end
    endtask

    initial begin
        $dumpfile("simulation.vcd");
        $dumpvars(0, tb_spi_flash_controller);

        // Initialize Inputs
        spi_ce = 0;
        i_ADDRESS_BUS = 16'h0000;
        i_RW = 1;

        i_DataBus = 8'h00; // Default value to prevent high-Z


        // Reset SPI Controller signals
        #100;

        // Stimulate SPI flash read for address 0x1234
        spi_flash_read(16'h3AAA);

        $display("Final SPI Data Received: %h", o_DATA);
        // Initialize Inputs
        spi_ce = 0;
        i_RW = 1;
        spi_flash_write(16'h3000, 8'hAA);
        $finish;
    end
endmodule

simulation.vcd
$date
	Thu Mar 27 20:57:03 2025
$end
$version
	Icarus Verilog
$end
$timescale
	1ns
$end
$scope module tb_spi_flash_controller $end
$var wire 1 ! o_SPI_MOSI $end
$var wire 1 " o_SPI_CS $end
$var wire 1 # o_SPI_CLK $end
$var wire 1 $ o_MemoryReady $end
$var wire 8 % o_DATA [7:0] $end
$var reg 1 & clk $end
$var reg 16 ' i_ADDRESS_BUS [15:0] $end
$var reg 8 ( i_DataBus [7:0] $end
$var reg 1 ) i_RW $end
$var reg 1 * i_SPI_MISO $end
$var reg 1 + reset $end
$var reg 1 , spi_ce $end
$scope module uut $end
$var wire 1 & clk $end
$var wire 16 - i_ADDRESS_BUS [15:0] $end
$var wire 8 . i_DataBus [7:0] $end
$var wire 1 ) i_RW $end
$var wire 1 * i_SPI_MISO $end
$var wire 1 + reset $end
$var wire 1 , spi_ce $end
$var wire 8 / spi_read_command [7:0] $end
$var wire 8 0 spi_write_command [7:0] $end
$var reg 6 1 bit_counter [5:0] $end
$var reg 1 2 clock_delay $end
$var reg 1 $ o_MemoryReady $end
$var reg 1 # o_SPI_CLK $end
$var reg 1 " o_SPI_CS $end
$var reg 1 ! o_SPI_MOSI $end
$var reg 8 3 o_spi_data [7:0] $end
$var reg 24 4 spi_address [23:0] $end
$var reg 8 5 spi_datawrite [7:0] $end
$var reg 1 6 spi_read_active $end
$var reg 1 7 spi_write_active $end
$upscope $end
$scope task spi_flash_read $end
$var reg 16 8 address [15:0] $end
$upscope $end
$scope task spi_flash_write $end
$var reg 16 9 address [15:0] $end
$var reg 8 : databus [7:0] $end
$upscope $end
$upscope $end
$enddefinitions $end
#0
$dumpvars
bx :
bx 9
bx 8
07
06
b0 5
b0 4
bx 3
02
b0 1
b10 0
b11 /
b0 .
b0 -
0,
x+
x*
1)
b0 (
b0 '
0&
bx %
x$
x#
x"
x!
$end
#6
1"
1$
0#
z!
1&
#12
0&
#18
1&
#24
0&
#30
1&
#36
0&
#42
1&
#48
0&
#54
1&
#60
0&
#66
1&
#72
0&
#78
1&
#84
0&
#90
1&
#96
0&
#100
1+
b11101010101010 8
#102
1&
#108
0&
#110
0+
#114
b0 %
b0 3
1&
#120
0&
1+
#126
1&
#132
0&
#138
1&
#144
0&
b11101010101010 '
b11101010101010 -
1,
#150
16
b101010101010 4
1&
#156
0&
#162
0!
12
0$
0"
1&
#168
0&
#174
b1 1
1#
1&
#180
0&
#186
0#
1&
#192
0&
#198
b10 1
1#
1&
#204
0&
#210
0#
1&
#216
0&
#222
b11 1
1#
1&
#228
0&
#234
0#
1&
#240
0&
#246
b100 1
1#
1&
#252
0&
#258
0#
1&
#264
0&
#270
b101 1
1#
1&
#276
0&
#282
0#
1&
#288
0&
#294
b110 1
1#
1&
#300
0&
#306
1!
0#
1&
#312
0&
#318
b111 1
1#
1&
#324
0&
#330
0#
1&
#336
0&
#342
b1000 1
1#
1&
#348
0&
#354
0!
0#
1&
#360
0&
#366
b1001 1
1#
1&
#372
0&
#378
0#
1&
#384
0&
#390
b1010 1
1#
1&
#396
0&
#402
0#
1&
#408
0&
#414
b1011 1
1#
1&
#420
0&
#426
0#
1&
#432
0&
#438
b1100 1
1#
1&
#444
0&
#450
0#
1&
#456
0&
#462
b1101 1
1#
1&
#468
0&
#474
0#
1&
#480
0&
#486
b1110 1
1#
1&
#492
0&
#498
0#
1&
#504
0&
#510
b1111 1
1#
1&
#516
0&
#522
0#
1&
#528
0&
#534
b10000 1
1#
1&
#540
0&
#546
0#
1&
#552
0&
#558
b10001 1
1#
1&
#564
0&
#570
0#
1&
#576
0&
#582
b10010 1
1#
1&
#588
0&
#594
0#
1&
#600
0&
#606
b10011 1
1#
1&
#612
0&
#618
0#
1&
#624
0&
#630
b10100 1
1#
1&
#636
0&
#642
1!
0#
1&
#648
0&
#654
b10101 1
1#
1&
#660
0&
#666
0!
0#
1&
#672
0&
#678
b10110 1
1#
1&
#684
0&
#690
1!
0#
1&
#696
0&
#702
b10111 1
1#
1&
#708
0&
#714
0!
0#
1&
#720
0&
#726
b11000 1
1#
1&
#732
0&
#738
1!
0#
1&
#744
0&
#750
b11001 1
1#
1&
#756
0&
#762
0!
0#
1&
#768
0&
#774
b11010 1
1#
1&
#780
0&
#786
1!
0#
1&
#792
0&
#798
b11011 1
1#
1&
#804
0&
#810
0!
0#
1&
#816
0&
#822
b11100 1
1#
1&
#828
0&
#834
1!
0#
1&
#840
0&
#846
b11101 1
1#
1&
#852
0&
#858
0!
0#
1&
#864
0&
#870
b11110 1
1#
1&
#876
0&
#882
1!
0#
1&
#888
0&
#894
b11111 1
1#
1&
#900
0&
#906
0!
0#
1&
#912
0&
#918
b100000 1
1#
1&
#924
0&
#930
0#
1&
#936
0&
#942
b100001 1
b10000000 %
b10000000 3
1#
1&
1*
#948
0&
#954
0#
1&
#960
0&
#966
b100010 1
b11000000 %
b11000000 3
1#
1&
#972
0&
#978
0#
1&
#984
0&
#990
b100011 1
b11100000 %
b11100000 3
1#
1&
#996
0&
#1002
0#
1&
#1008
0&
#1014
b100100 1
b11110000 %
b11110000 3
1#
1&
#1020
0&
#1026
0#
1&
#1032
0&
#1038
b100101 1
b11111000 %
b11111000 3
1#
1&
#1044
0&
#1050
0#
1&
#1056
0&
#1062
b100110 1
1#
1&
0*
#1068
0&
#1074
0#
1&
#1080
0&
#1086
b100111 1
b11111010 %
b11111010 3
1#
1&
1*
#1092
0&
#1098
0#
1&
#1104
0&
#1110
b101000 1
1#
1&
0,
0*
#1116
0&
#1122
1$
06
0#
1&
#1128
0&
#1134
1"
z!
1&
#1140
0&
#1146
1&
#1152
0&
#1158
1&
#1164
0&
#1170
1&
#1176
0&
#1182
1&
#1188
0&
#1194
1&
#1200
0&
#1206
1&
#1210
b10101010 :
b11000000000000 9
#1212
0&
#1218
1&
#1224
0&
#1230
1&
#1236
0&
#1242
1&
#1248
0&
#1254
1&
#1260
0&
#1266
1&
#1272
0&
#1278
1&
#1282
b10101010 (
b10101010 .
b11000000000000 '
b11000000000000 -
1,
0)
#1284
0&
#1290
b10101010 5
02
b0 1
17
b0 4
1&
#1296
0&
#1302
0!
12
0$
0"
1&
#1308
0&
#1314
b1 1
1#
1&
#1320
0&
#1326
0#
1&
#1332
0&
#1338
b10 1
1#
1&
#1344
0&
#1350
0#
1&
#1356
0&
#1362
b11 1
1#
1&
#1368
0&
#1374
0#
1&
#1380
0&
#1386
b100 1
1#
1&
#1392
0&
#1398
0#
1&
#1404
0&
#1410
b101 1
1#
1&
#1416
0&
#1422
0#
1&
#1428
0&
#1434
b110 1
1#
1&
#1440
0&
#1446
1!
0#
1&
#1452
0&
#1458
b111 1
1#
1&
#1464
0&
#1470
0!
0#
1&
#1476
0&
#1482
b1000 1
1#
1&
#1488
0&
#1494
0#
1&
#1500
0&
#1506
b1001 1
1#
1&
#1512
0&
#1518
0#
1&
#1524
0&
#1530
b1010 1
1#
1&
#1536
0&
#1542
0#
1&
#1548
0&
#1554
b1011 1
1#
1&
#1560
0&
#1566
0#
1&
#1572
0&
#1578
b1100 1
1#
1&
#1584
0&
#1590
0#
1&
#1596
0&
#1602
b1101 1
1#
1&
#1608
0&
#1614
0#
1&
#1620
0&
#1626
b1110 1
1#
1&
#1632
0&
#1638
0#
1&
#1644
0&
#1650
b1111 1
1#
1&
#1656
0&
#1662
0#
1&
#1668
0&
#1674
b10000 1
1#
1&
#1680
0&
#1686
0#
1&
#1692
0&
#1698
b10001 1
1#
1&
#1704
0&
#1710
0#
1&
#1716
0&
#1722
b10010 1
1#
1&
#1728
0&
#1734
0#
1&
#1740
0&
#1746
b10011 1
1#
1&
#1752
0&
#1758
0#
1&
#1764
0&
#1770
b10100 1
1#
1&
#1776
0&
#1782
0#
1&
#1788
0&
#1794
b10101 1
1#
1&
#1800
0&
#1806
0#
1&
#1812
0&
#1818
b10110 1
1#
1&
#1824
0&
#1830
0#
1&
#1836
0&
#1842
b10111 1
1#
1&
#1848
0&
#1854
0#
1&
#1860
0&
#1866
b11000 1
1#
1&
#1872
0&
#1878
0#
1&
#1884
0&
#1890
b11001 1
1#
1&
#1896
0&
#1902
0#
1&
#1908
0&
#1914
b11010 1
1#
1&
#1920
0&
#1926
0#
1&
#1932
0&
#1938
b11011 1
1#
1&
#1944
0&
#1950
0#
1&
#1956
0&
#1962
b11100 1
1#
1&
#1968
0&
#1974
0#
1&
#1980
0&
#1986
b11101 1
1#
1&
#1992
0&
#1998
0#
1&
#2004
0&
#2010
b11110 1
1#
1&
#2016
0&
#2022
0#
1&
#2028
0&
#2034
b11111 1
1#
1&
#2040
0&
#2046
0#
1&
#2052
0&
#2058
b100000 1
1#
1&
#2064
0&
#2070
1!
0#
1&
#2076
0&
#2082
b100001 1
1#
1&
#2088
0&
#2094
0!
0#
1&
#2100
0&
#2106
b100010 1
1#
1&
#2112
0&
#2118
1!
0#
1&
#2124
0&
#2130
b100011 1
1#
1&
#2136
0&
#2142
0!
0#
1&
#2148
0&
#2154
b100100 1
1#
1&
#2160
0&
#2166
1!
0#
1&
#2172
0&
#2178
b100101 1
1#
1&
#2184
0&
#2190
0!
0#
1&
#2196
0&
#2202
b100110 1
1#
1&
#2208
0&
#2214
1!
0#
1&
#2220
0&
#2226
b100111 1
1#
1&
#2232
0&
#2238
0!
0#
1&
#2244
0&
#2248
1)
0,
#2250
b101000 1
1#
1&
#2256
0&
#2262
1$
07
0#
1&
#2268
0&
#2274
1"
z!
1&
