FlashSpi.v
// SPI device uses SPI Mode 0, with active low Chip Select
module spi_flash_controller (
    input spi_ce,            // SPI chip select signal from address decoder
    input reset,             
    input [15:0] i_ADDRESS_BUS, // Address from 6809 (16 bits)
    input i_RW,               // Read/Write control signal (only reads for flash)
    input clk,                // System clock
    input i_SPI_MISO,         // SPI Master In Slave Out
    output reg o_SPI_CLK,     // SPI Clock
    output reg o_SPI_MOSI,    // SPI Master Out Slave In
    output reg o_SPI_CS,      // SPI Chip Select (active low)
    output reg [7:0] o_DATA,  // Data output to 6809
    output reg o_MemoryReady
);

    wire [7:0] spi_command = 8'h03; // Command for SPI flash (READ command is 0x03)
    reg [23:0] spi_address = 24'b0; // Address for SPI flash (24 bits)
    reg [23:0] last_spi_address = 24'b0; // Last address for SPI flash
    reg [7:0] spi_data = 8'b0;        // Data read from SPI flash
    reg [5:0] bit_counter = 6'd0;     // Tracks SPI transaction progress (6 bits to cover up to 40)
    reg spi_active = 0;               // Indicates SPI operation is active

    always @(posedge clk) begin
        if (~reset) begin
            spi_address <= 24'b0;     // Reset address
            last_spi_address <= 24'b0; // Reset address
            spi_data <= 8'b0;          // Reset data
            bit_counter <= 6'b0;       // Reset bit counter
            spi_active <= 1'b0;        // Reset SPI active flag
            o_SPI_CLK = 1'b0;         // Reset SPI clock
        end

        // Start SPI transaction when chip select is active and it's a read cycle
        if (spi_ce && i_RW && !spi_active && reset) begin
            spi_address <= {12'b0, i_ADDRESS_BUS[11:0]}; // Lower 12 bits of address to 24-bit SPI address
            if (spi_address != last_spi_address) begin
                spi_active <= 1'b1;         // Mark SPI as active
                last_spi_address <= spi_address; // Store the last address
                bit_counter <= 6'd0;        // Reset bit counter
                
            end
        end

        if (spi_active && reset) begin
            o_SPI_CS <= 1'b0;           // Activate SPI chip select
            o_MemoryReady <= 1'b0;     // Keep 6809 in wait state during SPI transaction
            if (bit_counter > 6'd0) begin 
                o_SPI_CLK = ~o_SPI_CLK;   // Toggle SPI clock
            end


            if (~o_SPI_CLK) begin
                // On rising edge of SPI clock, handle data transfer
                if (bit_counter < 6'd8) begin
                    // Send SPI command (8 bits)
                    o_SPI_MOSI <= spi_command[7 - bit_counter];
                end else if (bit_counter < 6'd32) begin
                    // Send 24-bit SPI address (address starts at bit 8)
                    o_SPI_MOSI <= spi_address[31 - bit_counter];
                end else if (bit_counter < 6'd40) begin
                    // Receive 8-bit data (after address)
                    spi_data[7 - (bit_counter - 6'd32)] <= i_SPI_MISO;
                end

                // Increment bit counter (always within 6-bit range, safe to truncate)
                bit_counter <= bit_counter + 1;

                if (bit_counter == 6'd40) begin
                    // End of SPI transaction
                    spi_active <= 1'b0;      // Mark SPI as inactive
                    o_DATA <= spi_data;      // Output received data to 6809
                end
            end
        end else begin
            // Idle state: set SPI signals to default
            o_SPI_MOSI <= 1'bz;        // High Impedance at idle
            o_SPI_CLK <= 1'b0;         // Clock low in idle (for SPI Mode 0)
            o_MemoryReady <= 1'b1;     // Allow the 6809 to continue
            o_SPI_CS <= 1'b1;        // Deactivate SPI chip select
            
        end
    end
endmodule

TB_FlashSpi.v
`timescale 1ns / 1ns
module tb_spi_flash_controller;

    reg spi_ce;
    reg reset;
    reg [15:0] i_ADDRESS_BUS;
    reg i_RW;
    reg clk;
    reg i_SPI_MISO;
    wire o_SPI_CLK;
    wire o_SPI_MOSI;
    wire o_SPI_CS;
    wire [7:0] o_DATA;
    wire o_MemoryReady;

    // Instantiate the Unit Under Test (UUT)
    spi_flash_controller uut (
        .spi_ce(spi_ce),
        .reset(reset),
        .i_ADDRESS_BUS(i_ADDRESS_BUS),
        .i_RW(i_RW),
        .clk(clk),
        .i_SPI_MISO(i_SPI_MISO),
        .o_SPI_CLK(o_SPI_CLK),
        .o_SPI_MOSI(o_SPI_MOSI),
        .o_SPI_CS(o_SPI_CS),
        .o_DATA(o_DATA),
        .o_MemoryReady(o_MemoryReady)
    );

    // Clock generation at 88.67 MHz 
    localparam CLOCK_PERIOD_NS = 11.285; // 88.67 MHz 
    initial clk = 0;
    always #(CLOCK_PERIOD_NS / 2) clk = ~clk;

    // Simulation task for SPI flash read operation
    task spi_flash_read(input [15:0] address);
        begin
            reset = 1;
            #10;
            reset = 0;
            #10;
            reset = 1;
            #24;
            spi_ce = 1;
            i_ADDRESS_BUS = address;
            #762;  // Wait for SPI operation to begin
            #24 i_SPI_MISO = 1;
            #24 i_SPI_MISO = 1;
            #24 i_SPI_MISO = 1;
            #24 i_SPI_MISO = 1;
            #24 i_SPI_MISO = 1;
            #24 i_SPI_MISO = 0;
            #24 i_SPI_MISO = 1;
            #24 i_SPI_MISO = 0;
            spi_ce = 0;
            i_RW = 0;
            #100;  // Return to idle state after operation
        end
    endtask

    initial begin
        $dumpfile("simulation.vcd");
        $dumpvars(0, tb_spi_flash_controller);

        // Initialize Inputs
        spi_ce = 0;
        i_ADDRESS_BUS = 16'h0000;
        i_RW = 1;
        i_SPI_MISO = 0;

        // Reset SPI Controller signals
        #100;

        // Stimulate SPI flash read for address 0x1234
        spi_flash_read(16'h3AAA);

        $display("Final SPI Data Received: %h", o_DATA);
        $finish;
    end
endmodule

simulation.vcd
$date
	Mon Mar 17 14:32:52 2025
$end
$version
	Icarus Verilog
$end
$timescale
	1ns
$end
$scope module tb_spi_flash_controller $end
$var wire 1 ! o_SPI_MOSI $end
$var wire 1 " o_SPI_CS $end
$var wire 1 # o_SPI_CLK $end
$var wire 1 $ o_MemoryReady $end
$var wire 8 % o_DATA [7:0] $end
$var reg 1 & clk $end
$var reg 16 ' i_ADDRESS_BUS [15:0] $end
$var reg 1 ( i_RW $end
$var reg 1 ) i_SPI_MISO $end
$var reg 1 * reset $end
$var reg 1 + spi_ce $end
$scope module uut $end
$var wire 1 & clk $end
$var wire 16 , i_ADDRESS_BUS [15:0] $end
$var wire 1 ( i_RW $end
$var wire 1 ) i_SPI_MISO $end
$var wire 1 * reset $end
$var wire 1 + spi_ce $end
$var wire 8 - spi_command [7:0] $end
$var reg 6 . bit_counter [5:0] $end
$var reg 24 / last_spi_address [23:0] $end
$var reg 8 0 o_DATA [7:0] $end
$var reg 1 $ o_MemoryReady $end
$var reg 1 # o_SPI_CLK $end
$var reg 1 " o_SPI_CS $end
$var reg 1 ! o_SPI_MOSI $end
$var reg 1 1 spi_active $end
$var reg 24 2 spi_address [23:0] $end
$var reg 8 3 spi_data [7:0] $end
$upscope $end
$scope task spi_flash_read $end
$var reg 16 4 address [15:0] $end
$upscope $end
$upscope $end
$enddefinitions $end
#0
$dumpvars
bx 4
b0 3
b0 2
01
bx 0
b0 /
b0 .
b11 -
b0 ,
0+
x*
0)
1(
b0 '
0&
bx %
x$
x#
x"
x!
$end
#6
1"
1$
0#
z!
1&
#12
0&
#18
1&
#24
0&
#30
1&
#36
0&
#42
1&
#48
0&
#54
1&
#60
0&
#66
1&
#72
0&
#78
1&
#84
0&
#90
1&
#96
0&
#100
1*
b11101010101010 4
#102
1&
#108
0&
#110
0*
#114
1&
#120
0&
1*
#126
1&
#130
b11101010101010 '
b11101010101010 ,
1+
#132
0&
#138
b101010101010 2
1&
#144
0&
#150
b101010101010 /
11
1&
#156
0&
#162
b1 .
0!
0$
0"
1&
#168
0&
#174
1#
1&
#180
0&
#186
b10 .
0#
1&
#192
0&
#198
1#
1&
#204
0&
#210
b11 .
0#
1&
#216
0&
#222
1#
1&
#228
0&
#234
b100 .
0#
1&
#240
0&
#246
1#
1&
#252
0&
#258
b101 .
0#
1&
#264
0&
#270
1#
1&
#276
0&
#282
b110 .
0#
1&
#288
0&
#294
1#
1&
#300
0&
#306
b111 .
1!
0#
1&
#312
0&
#318
1#
1&
#324
0&
#330
b1000 .
0#
1&
#336
0&
#342
1#
1&
#348
0&
#354
b1001 .
0!
0#
1&
#360
0&
#366
1#
1&
#372
0&
#378
b1010 .
0#
1&
#384
0&
#390
1#
1&
#396
0&
#402
b1011 .
0#
1&
#408
0&
#414
1#
1&
#420
0&
#426
b1100 .
0#
1&
#432
0&
#438
1#
1&
#444
0&
#450
b1101 .
0#
1&
#456
0&
#462
1#
1&
#468
0&
#474
b1110 .
0#
1&
#480
0&
#486
1#
1&
#492
0&
#498
b1111 .
0#
1&
#504
0&
#510
1#
1&
#516
0&
#522
b10000 .
0#
1&
#528
0&
#534
1#
1&
#540
0&
#546
b10001 .
0#
1&
#552
0&
#558
1#
1&
#564
0&
#570
b10010 .
0#
1&
#576
0&
#582
1#
1&
#588
0&
#594
b10011 .
0#
1&
#600
0&
#606
1#
1&
#612
0&
#618
b10100 .
0#
1&
#624
0&
#630
1#
1&
#636
0&
#642
b10101 .
1!
0#
1&
#648
0&
#654
1#
1&
#660
0&
#666
b10110 .
0!
0#
1&
#672
0&
#678
1#
1&
#684
0&
#690
b10111 .
1!
0#
1&
#696
0&
#702
1#
1&
#708
0&
#714
b11000 .
0!
0#
1&
#720
0&
#726
1#
1&
#732
0&
#738
b11001 .
1!
0#
1&
#744
0&
#750
1#
1&
#756
0&
#762
b11010 .
0!
0#
1&
#768
0&
#774
1#
1&
#780
0&
#786
b11011 .
1!
0#
1&
#792
0&
#798
1#
1&
#804
0&
#810
b11100 .
0!
0#
1&
#816
0&
#822
1#
1&
#828
0&
#834
b11101 .
1!
0#
1&
#840
0&
#846
1#
1&
#852
0&
#858
b11110 .
0!
0#
1&
#864
0&
#870
1#
1&
#876
0&
#882
b11111 .
1!
0#
1&
#888
0&
#894
1#
1&
#900
0&
#906
b100000 .
0!
0#
1&
#912
0&
#918
1#
1&
#924
0&
#930
b100001 .
0#
1&
#936
0&
#942
1#
1&
#948
0&
#954
b100010 .
0#
1&
#960
0&
#966
1#
1&
#972
0&
#978
b100011 .
0#
1&
#984
0&
#990
1#
1&
#996
0&
#1002
b100100 .
0#
1&
#1008
0&
#1014
1#
1&
#1020
0&
#1026
b100101 .
0#
1&
#1032
0&
#1036
1)
#1038
1#
1&
#1044
0&
#1050
b100110 .
b100 3
0#
1&
#1056
0&
#1060
0)
#1062
1#
1&
#1068
0&
#1074
b100111 .
0#
1&
#1080
0&
#1084
0(
0+
1)
#1086
1#
1&
#1092
0&
#1098
b101000 .
b101 3
0#
1&
#1104
0&
#1110
1#
1&
#1116
0&
#1122
b101 %
b101 0
01
b101001 .
0#
1&
#1128
0&
#1134
1"
1$
z!
1&
