FlashSpi.v
// SPI device uses SPI Mode 0, with active low Chip Select
// Max speed rating of SPI Flash with read instruction is 50MHz. 
module spi_flash_controller (
    input spi_ce,            // SPI chip select signal from address decoder
    input reset,             // Reset signal
    input i_enable,
    input [15:0] i_ADDRESS_BUS, // Address from 6809 (16 bits)
    input [7:0] i_DataBus,  // Data input from 6809
    input i_RW,               // Read/Write control signal (only reads for flash)
    input clk,                // System clock
    input i_SPI_MISO,         // SPI Master In Slave Out
    output reg o_SPI_CLK,     // SPI Clock
    output reg o_SPI_MOSI,    // SPI Master Out Slave In
    output reg o_SPI_CS,      // SPI Chip Select (active low)
    output reg [7:0] o_spi_data,  // Data output to 6809
    output reg o_MemoryReady,
    output reg o_HALT,
    output reg [7:0] spi_datawrite          // Data to write to SPI flash
);

    wire [7:0] spi_read_command = 8'h03; // Command for SPI flash (READ command is 0x03)
    wire [7:0] spi_page_command = 8'h02; // Command for SPI flash (WRITE PAGE command is 0x02)
    wire [7:0] spi_write_enable_command = 8'h06; // Command for SPI flash (WRITE ENABLE command is 0x06)
    reg [23:0] spi_readaddress = 24'b0; // Address for SPI flash (24 bits)
    reg [23:0] spi_writeaddress = 24'b0; // Address for SPI flash (24 bits)
    reg [5:0] bit_counter = 6'd0;     // Tracks SPI transaction progress (6 bits to cover up to 40)
    reg [15:0] writedelay_counter = 0;
    reg spi_read_active = 0;               // Indicates SPI read operation is active
    reg spi_write_active = 0;               // Indicates SPI write enable operation is active
    reg start_write_delay = 0;
    reg spi_page_active = 0;               // Indicates SPI page operation is active
    reg clock_delay = 0;
    reg start_write = 0;
    reg start_read = 0;
    // SPI flash controller logic
    // Reset logic

    always @(negedge i_enable) begin
        if (!i_RW && spi_ce) begin
            spi_writeaddress <= {12'b0, i_ADDRESS_BUS[11:0]}; // Lower 12 bits of address to 24-bit SPI address
            start_write <= 1'b1;
            spi_datawrite <= i_DataBus;
        end
        else begin
            start_write <= 1'b0;
        end
    end

    always @(posedge i_enable) begin
        if (i_RW && spi_ce) begin
            spi_readaddress <= {12'b0, i_ADDRESS_BUS[11:0]}; // Lower 12 bits of address to 24-bit SPI address
            start_read <= 1'b1;
        end
        else begin
            start_read <= 1'b0;
        end
    end


    always @(posedge clk) begin
        if (~reset) begin
            o_spi_data <= 8'b0;          // Reset data
            bit_counter <= 6'b0;       // Reset bit counter
            spi_read_active <= 1'b0;        // Reset SPI read active flag
            spi_write_active <= 1'b0;        // Reset SPI write active flag
            spi_page_active <= 1'b0;        // Reset SPI page active flag
            o_MemoryReady <= 1'b1;    // Allow the 6809 to continue
            o_HALT <= 1'b1;         // Deactivate HALT signal
        end

        // Start SPI transaction when chip select is active and it's a read cycle
        if (start_read && !spi_read_active && reset) begin
            if(spi_write_active || start_write_delay) begin
               o_HALT <= 1'b0;         // Activate HALT signal
            end
            else begin
                spi_read_active <= 1'b1;         // Mark SPI as active
                bit_counter <= 6'd0;        // Reset bit counter
                clock_delay <= 1'b0;
                o_HALT <= 1'b1;         // Deactivate HALT signal
            end

       end
       else if (start_write && !spi_write_active && !spi_page_active && !spi_read_active && reset) begin
            spi_write_active <= 1'b1;         // Mark write enable as active
            spi_page_active <= 1'b0;         // Mark page as inactive
            bit_counter <= 6'd0;        // Reset bit counter
            clock_delay <= 1'b0;
        end

        
        // Read data from SPI flash
        if (spi_read_active && reset) begin
            o_SPI_CS <= 1'b0;           // Activate SPI chip select
            o_MemoryReady <= 1'b0;     // Keep 6809 in wait state during SPI transaction

            if (clock_delay) begin 
                o_SPI_CLK = ~o_SPI_CLK;   // Toggle SPI clock
            end
            clock_delay <= 1'b1;

            if (~o_SPI_CLK) begin
                // On rising edge of SPI clock, handle data transfer
                if (bit_counter < 6'd8) begin //7
                    // Send SPI command (8 bits)
                    o_SPI_MOSI <= spi_read_command[7 - bit_counter];
                end else if (bit_counter < 6'd32) begin
                    // Send 24-bit SPI address (address starts at bit 8)
                    o_SPI_MOSI <= spi_readaddress[31 - bit_counter];
                end else if (bit_counter == 6'd40) begin
                    // End of SPI transaction
                    spi_read_active <= 1'b0;      // Mark SPI as inactive
                    o_MemoryReady <= 1'b1;     // Allow the 6809 to continue
                end
            end
            else begin
                if (bit_counter < 6'd40) begin
                    // Receive 8-bit data (after address)
                    o_spi_data[7 - (bit_counter - 6'd32)] <= i_SPI_MISO;
                end
                // Increment bit counter (always within 6-bit range, safe to truncate)
                bit_counter <= bit_counter + 1;
            end
        end 
        // Enable Write data to SPI flash
        else if (spi_write_active && !spi_page_active && reset) begin
            o_SPI_CS <= 1'b0;           // Activate SPI chip select
            if (clock_delay) begin 
                o_SPI_CLK = ~o_SPI_CLK;   // Toggle SPI clock
            end
            clock_delay <= 1'b1;

            if (~o_SPI_CLK) begin
                // On rising edge of SPI clock, handle data transfer
                if (bit_counter < 6'd8) begin //7
                    // Send SPI command (8 bits)
                    o_SPI_MOSI <= spi_write_enable_command[7 - bit_counter];
                end  
            end
            else begin
                if (bit_counter == 6'd8) begin
                    // End of SPI transaction
                    spi_page_active <= 1'b1;      // Mark SPI page active
                    bit_counter <= 6'd0;        // Reset bit counter
                    clock_delay <= 1'b0;
                    o_SPI_CS <= 1'b1;           // Deactivate SPI chip select
                    o_SPI_CLK <= 1'b0;         // Clock low in idle (for SPI Mode 0)
                end
                // Increment bit counter (always within 6-bit range, safe to truncate)
                else begin
                bit_counter <= bit_counter + 1;
                end
            end
        end
        // Write data to SPI flash
        else if (spi_page_active && reset) begin
            o_SPI_CS <= 1'b0;           // Activate SPI chip select
           
            if (clock_delay) begin 
                o_SPI_CLK = ~o_SPI_CLK;   // Toggle SPI clock
            end
            clock_delay <= 1'b1;

            if (~o_SPI_CLK) begin
                // On rising edge of SPI clock, handle data transfer
                if (bit_counter < 6'd8) begin //7
                    // Send SPI command (8 bits)
                    o_SPI_MOSI <= spi_page_command[7 - bit_counter];
                end else if (bit_counter < 6'd32) begin
                    // Send 24-bit SPI address (address starts at bit 8)
                    o_SPI_MOSI <= spi_writeaddress[31 - bit_counter];

                end
                else if (bit_counter < 6'd40) begin
                // Receive 8-bit data (after address)
                o_SPI_MOSI <= spi_datawrite[7 - (bit_counter - 6'd32)];
                end    
                else if (bit_counter == 6'd40) begin
                    // End of SPI transaction
                    spi_page_active <= 1'b0;      // Mark SPI as inactive
                    spi_write_active <= 1'b0;      // Delay finished for write. 
                    writedelay_counter <= 16'd100;  // Set counter for 6ms @ 8MHz max time for write on a 25LC1024 eeprom, changed to 48000 to 100 for test.
                    start_write_delay <= 1'b1;
                end
            end
            else begin
                // Increment bit counter (always within 6-bit range, safe to truncate)
                bit_counter <= bit_counter + 1;
            end
        end 
        else begin
            // Idle state: set SPI signals to default
            o_SPI_MOSI <= 1'bz;        // High Impedance at idle
            o_SPI_CLK <= 1'b0;         // Clock low in idle (for SPI Mode 0)
            o_MemoryReady <= 1'b1;     // Allow the 6809 to continue
            o_HALT <= 1'b1;         // Deactivate HALT signal
            o_SPI_CS <= 1'b1;        // Deactivate SPI chip select
            if(start_write_delay) begin
                if (writedelay_counter > 0) begin
                writedelay_counter <= writedelay_counter - 1; // count down to zero for delay
                end 
                else begin
                    start_write_delay <= 1'b0;
                end
            end

        end
    end
endmodule

TB_FlashSpi.v
`timescale 1ns / 1ns
module tb_spi_flash_controller;

    reg spi_ce;
    reg reset;
    reg [15:0] i_ADDRESS_BUS;
    reg [7:0] i_DataBus;
    reg i_RW;
    reg clk;
    reg i_SPI_MISO;
    wire o_SPI_CLK;
    wire o_SPI_MOSI;
    wire o_SPI_CS;
    wire [7:0] o_DATA;
    wire o_MemoryReady;
    wire o_HALT;
    reg i_enable;

    // Instantiate the Unit Under Test (UUT)
    spi_flash_controller uut (
        .spi_ce(spi_ce),
        .reset(reset),
        .i_enable(i_enable),
        .i_ADDRESS_BUS(i_ADDRESS_BUS),
        .i_DataBus(i_DataBus),
        .i_RW(i_RW),
        .clk(clk),
        .i_SPI_MISO(i_SPI_MISO),
        .o_SPI_CLK(o_SPI_CLK),
        .o_SPI_MOSI(o_SPI_MOSI),
        .o_SPI_CS(o_SPI_CS),
        .o_spi_data(o_DATA),
        .o_MemoryReady(o_MemoryReady),
        .o_HALT(o_HALT)
    );

    // Clock generation at 88.67 MHz 
    localparam CLOCK_PERIOD_NS = 11.285; // 88.67 MHz 
    initial clk = 0;
    always #(CLOCK_PERIOD_NS / 2) clk = ~clk;

    // Simulation task for SPI flash read operation
    task spi_flash_read(input [15:0] address);
        begin
            #24;
            spi_ce = 1;
            i_ADDRESS_BUS = address;
            i_RW = 1;  // Read operation
            #10;
            i_enable = 1;
            #10;
            i_enable = 0;
            spi_ce = 0;
            #10;
            i_enable = 1;
            #10;
            i_enable = 0;
            #774;  // Wait for SPI operation to begin
            #24 i_SPI_MISO = 1;
            #24 i_SPI_MISO = 1;
            #24 i_SPI_MISO = 1;
            #24 i_SPI_MISO = 1;
            #24 i_SPI_MISO = 1;
            #24 i_SPI_MISO = 0;
            #24 i_SPI_MISO = 1;
            #24 i_SPI_MISO = 0;
            i_RW = 1;
        end
    endtask
    // Simulation task for SPI flash read operation
    task spi_flash_write(input [15:0] address, input [7:0] databus);
        begin
            #24;
            #24;
            #24;
            i_RW = 0;
            spi_ce = 1;
            #10;
            i_enable = 1;
            i_ADDRESS_BUS = address;
            i_DataBus = databus;
            #10;
            i_enable = 0;

            #10;
            i_enable = 1;
            spi_ce = 0;
            i_RW = 1;
            #10;
            i_enable = 0;
            #3550;  // Wait for SPI operation to begin

           // #15000;  // Return to idle state after operation
        end
    endtask

    initial begin
        $dumpfile("simulation.vcd");
        $dumpvars(0, tb_spi_flash_controller);

        // Initialize Inputs
        spi_ce = 0;
        i_ADDRESS_BUS = 16'h0000;
        i_RW = 1;
        reset = 1;
        #10;
        reset = 0;
        #10;
        reset = 1;
        i_DataBus = 8'h00; // Default value to prevent high-Z
        // Reset SPI Controller signals
        #100;
        // Stimulate SPI flash read for address 0x1234
        spi_flash_read(16'h3AAA);
        #100;  // Return to idle state after operation
        $display("Final SPI Data Received: %h", o_DATA);
        // Initialize Inputs
        spi_flash_write(16'h3000, 8'hAA);
        $finish;
    end
endmodule

simulation.vcd
$date
	Sun May 18 22:29:50 2025
$end
$version
	Icarus Verilog
$end
$timescale
	1ns
$end
$scope module tb_spi_flash_controller $end
$var wire 1 ! o_SPI_MOSI $end
$var wire 1 " o_SPI_CS $end
$var wire 1 # o_SPI_CLK $end
$var wire 1 $ o_MemoryReady $end
$var wire 1 % o_HALT $end
$var wire 8 & o_DATA [7:0] $end
$var reg 1 ' clk $end
$var reg 16 ( i_ADDRESS_BUS [15:0] $end
$var reg 8 ) i_DataBus [7:0] $end
$var reg 1 * i_RW $end
$var reg 1 + i_SPI_MISO $end
$var reg 1 , i_enable $end
$var reg 1 - reset $end
$var reg 1 . spi_ce $end
$scope module uut $end
$var wire 1 ' clk $end
$var wire 16 / i_ADDRESS_BUS [15:0] $end
$var wire 8 0 i_DataBus [7:0] $end
$var wire 1 * i_RW $end
$var wire 1 + i_SPI_MISO $end
$var wire 1 , i_enable $end
$var wire 1 - reset $end
$var wire 1 . spi_ce $end
$var wire 8 1 spi_page_command [7:0] $end
$var wire 8 2 spi_read_command [7:0] $end
$var wire 8 3 spi_write_enable_command [7:0] $end
$var reg 6 4 bit_counter [5:0] $end
$var reg 1 5 clock_delay $end
$var reg 1 % o_HALT $end
$var reg 1 $ o_MemoryReady $end
$var reg 1 # o_SPI_CLK $end
$var reg 1 " o_SPI_CS $end
$var reg 1 ! o_SPI_MOSI $end
$var reg 8 6 o_spi_data [7:0] $end
$var reg 8 7 spi_datawrite [7:0] $end
$var reg 1 8 spi_page_active $end
$var reg 1 9 spi_read_active $end
$var reg 24 : spi_readaddress [23:0] $end
$var reg 1 ; spi_write_active $end
$var reg 24 < spi_writeaddress [23:0] $end
$var reg 1 = start_read $end
$var reg 1 > start_write $end
$var reg 1 ? start_write_delay $end
$var reg 16 @ writedelay_counter [15:0] $end
$upscope $end
$scope task spi_flash_read $end
$var reg 16 A address [15:0] $end
$upscope $end
$scope task spi_flash_write $end
$var reg 16 B address [15:0] $end
$var reg 8 C databus [7:0] $end
$upscope $end
$upscope $end
$enddefinitions $end
#0
$dumpvars
bx C
bx B
bx A
b0 @
0?
0>
0=
b0 <
0;
b0 :
09
08
bx 7
bx 6
05
b0 4
b110 3
b11 2
b10 1
bx 0
b0 /
0.
1-
x,
x+
1*
bx )
b0 (
0'
bx &
x%
x$
x#
x"
x!
$end
#6
1"
1%
1$
0#
z!
1'
#10
0-
#12
0'
#18
b0 &
b0 6
1'
#20
b0 )
b0 0
1-
#24
0'
#30
1'
#36
0'
#42
1'
#48
0'
#54
1'
#60
0'
#66
1'
#72
0'
#78
1'
#84
0'
#90
1'
#96
0'
#102
1'
#108
0'
#114
1'
#120
0'
b11101010101010 A
#126
1'
#132
0'
#138
1'
#144
0'
b11101010101010 (
b11101010101010 /
1.
#150
1'
#154
1=
b101010101010 :
1,
#156
0'
#162
19
1'
#164
0.
0,
#168
0'
#174
0!
15
0$
0"
0=
1'
1,
#180
0'
#184
0,
#186
b1 4
1#
1'
#192
0'
#198
0#
1'
#204
0'
#210
b10 4
1#
1'
#216
0'
#222
0#
1'
#228
0'
#234
b11 4
1#
1'
#240
0'
#246
0#
1'
#252
0'
#258
b100 4
1#
1'
#264
0'
#270
0#
1'
#276
0'
#282
b101 4
1#
1'
#288
0'
#294
0#
1'
#300
0'
#306
b110 4
1#
1'
#312
0'
#318
1!
0#
1'
#324
0'
#330
b111 4
1#
1'
#336
0'
#342
0#
1'
#348
0'
#354
b1000 4
1#
1'
#360
0'
#366
0!
0#
1'
#372
0'
#378
b1001 4
1#
1'
#384
0'
#390
0#
1'
#396
0'
#402
b1010 4
1#
1'
#408
0'
#414
0#
1'
#420
0'
#426
b1011 4
1#
1'
#432
0'
#438
0#
1'
#444
0'
#450
b1100 4
1#
1'
#456
0'
#462
0#
1'
#468
0'
#474
b1101 4
1#
1'
#480
0'
#486
0#
1'
#492
0'
#498
b1110 4
1#
1'
#504
0'
#510
0#
1'
#516
0'
#522
b1111 4
1#
1'
#528
0'
#534
0#
1'
#540
0'
#546
b10000 4
1#
1'
#552
0'
#558
0#
1'
#564
0'
#570
b10001 4
1#
1'
#576
0'
#582
0#
1'
#588
0'
#594
b10010 4
1#
1'
#600
0'
#606
0#
1'
#612
0'
#618
b10011 4
1#
1'
#624
0'
#630
0#
1'
#636
0'
#642
b10100 4
1#
1'
#648
0'
#654
1!
0#
1'
#660
0'
#666
b10101 4
1#
1'
#672
0'
#678
0!
0#
1'
#684
0'
#690
b10110 4
1#
1'
#696
0'
#702
1!
0#
1'
#708
0'
#714
b10111 4
1#
1'
#720
0'
#726
0!
0#
1'
#732
0'
#738
b11000 4
1#
1'
#744
0'
#750
1!
0#
1'
#756
0'
#762
b11001 4
1#
1'
#768
0'
#774
0!
0#
1'
#780
0'
#786
b11010 4
1#
1'
#792
0'
#798
1!
0#
1'
#804
0'
#810
b11011 4
1#
1'
#816
0'
#822
0!
0#
1'
#828
0'
#834
b11100 4
1#
1'
#840
0'
#846
1!
0#
1'
#852
0'
#858
b11101 4
1#
1'
#864
0'
#870
0!
0#
1'
#876
0'
#882
b11110 4
1#
1'
#888
0'
#894
1!
0#
1'
#900
0'
#906
b11111 4
1#
1'
#912
0'
#918
0!
0#
1'
#924
0'
#930
b100000 4
1#
1'
#936
0'
#942
0#
1'
#948
0'
#954
b100001 4
bx0000000 &
bx0000000 6
1#
1'
#960
0'
#966
0#
1'
#972
0'
#978
b100010 4
bx000000 &
bx000000 6
1#
1'
#982
1+
#984
0'
#990
0#
1'
#996
0'
#1002
b100011 4
bx100000 &
bx100000 6
1#
1'
#1008
0'
#1014
0#
1'
#1020
0'
#1026
b100100 4
bx110000 &
bx110000 6
1#
1'
#1032
0'
#1038
0#
1'
#1044
0'
#1050
b100101 4
bx111000 &
bx111000 6
1#
1'
#1056
0'
#1062
0#
1'
#1068
0'
#1074
b100110 4
bx111100 &
bx111100 6
1#
1'
#1080
0'
#1086
0#
1'
#1092
0'
#1098
b100111 4
bx111110 &
bx111110 6
1#
1'
#1102
0+
#1104
0'
#1110
0#
1'
#1116
0'
#1122
b101000 4
1#
1'
#1126
1+
#1128
0'
#1134
1$
09
0#
1'
#1140
0'
#1146
1"
z!
1'
#1150
0+
#1152
0'
#1158
1'
#1164
0'
#1170
1'
#1176
0'
#1182
1'
#1188
0'
#1194
1'
#1200
0'
#1206
1'
#1212
0'
#1218
1'
#1224
0'
#1230
1'
#1236
0'
#1242
1'
#1248
0'
#1250
b10101010 C
b11000000000000 B
#1254
1'
#1260
0'
#1266
1'
#1272
0'
#1278
1'
#1284
0'
#1290
1'
#1296
0'
#1302
1'
#1308
0'
#1314
1'
#1320
0'
#1322
1.
0*
#1326
1'
#1332
0'
b10101010 )
b10101010 0
b11000000000000 (
b11000000000000 /
1,
#1338
1'
#1342
b10101010 7
1>
0,
#1344
0'
#1350
05
b0 4
1;
1'
#1352
1*
0.
1,
#1356
0'
#1362
0!
15
0"
0>
1'
0,
#1368
0'
#1374
b1 4
1#
1'
#1380
0'
#1386
0#
1'
#1392
0'
#1398
b10 4
1#
1'
#1404
0'
#1410
0#
1'
#1416
0'
#1422
b11 4
1#
1'
#1428
0'
#1434
0#
1'
#1440
0'
#1446
b100 4
1#
1'
#1452
0'
#1458
0#
1'
#1464
0'
#1470
b101 4
1#
1'
#1476
0'
#1482
1!
0#
1'
#1488
0'
#1494
b110 4
1#
1'
#1500
0'
#1506
0#
1'
#1512
0'
#1518
b111 4
1#
1'
#1524
0'
#1530
0!
0#
1'
#1536
0'
#1542
b1000 4
1#
1'
#1548
0'
#1554
0#
1'
#1560
0'
#1566
1"
05
b0 4
18
0#
1'
#1572
0'
#1578
15
0"
1'
#1584
0'
#1590
b1 4
1#
1'
#1596
0'
#1602
0#
1'
#1608
0'
#1614
b10 4
1#
1'
#1620
0'
#1626
0#
1'
#1632
0'
#1638
b11 4
1#
1'
#1644
0'
#1650
0#
1'
#1656
0'
#1662
b100 4
1#
1'
#1668
0'
#1674
0#
1'
#1680
0'
#1686
b101 4
1#
1'
#1692
0'
#1698
0#
1'
#1704
0'
#1710
b110 4
1#
1'
#1716
0'
#1722
1!
0#
1'
#1728
0'
#1734
b111 4
1#
1'
#1740
0'
#1746
0!
0#
1'
#1752
0'
#1758
b1000 4
1#
1'
#1764
0'
#1770
0#
1'
#1776
0'
#1782
b1001 4
1#
1'
#1788
0'
#1794
0#
1'
#1800
0'
#1806
b1010 4
1#
1'
#1812
0'
#1818
0#
1'
#1824
0'
#1830
b1011 4
1#
1'
#1836
0'
#1842
0#
1'
#1848
0'
#1854
b1100 4
1#
1'
#1860
0'
#1866
0#
1'
#1872
0'
#1878
b1101 4
1#
1'
#1884
0'
#1890
0#
1'
#1896
0'
#1902
b1110 4
1#
1'
#1908
0'
#1914
0#
1'
#1920
0'
#1926
b1111 4
1#
1'
#1932
0'
#1938
0#
1'
#1944
0'
#1950
b10000 4
1#
1'
#1956
0'
#1962
0#
1'
#1968
0'
#1974
b10001 4
1#
1'
#1980
0'
#1986
0#
1'
#1992
0'
#1998
b10010 4
1#
1'
#2004
0'
#2010
0#
1'
#2016
0'
#2022
b10011 4
1#
1'
#2028
0'
#2034
0#
1'
#2040
0'
#2046
b10100 4
1#
1'
#2052
0'
#2058
0#
1'
#2064
0'
#2070
b10101 4
1#
1'
#2076
0'
#2082
0#
1'
#2088
0'
#2094
b10110 4
1#
1'
#2100
0'
#2106
0#
1'
#2112
0'
#2118
b10111 4
1#
1'
#2124
0'
#2130
0#
1'
#2136
0'
#2142
b11000 4
1#
1'
#2148
0'
#2154
0#
1'
#2160
0'
#2166
b11001 4
1#
1'
#2172
0'
#2178
0#
1'
#2184
0'
#2190
b11010 4
1#
1'
#2196
0'
#2202
0#
1'
#2208
0'
#2214
b11011 4
1#
1'
#2220
0'
#2226
0#
1'
#2232
0'
#2238
b11100 4
1#
1'
#2244
0'
#2250
0#
1'
#2256
0'
#2262
b11101 4
1#
1'
#2268
0'
#2274
0#
1'
#2280
0'
#2286
b11110 4
1#
1'
#2292
0'
#2298
0#
1'
#2304
0'
#2310
b11111 4
1#
1'
#2316
0'
#2322
0#
1'
#2328
0'
#2334
b100000 4
1#
1'
#2340
0'
#2346
1!
0#
1'
#2352
0'
#2358
b100001 4
1#
1'
#2364
0'
#2370
0!
0#
1'
#2376
0'
#2382
b100010 4
1#
1'
#2388
0'
#2394
1!
0#
1'
#2400
0'
#2406
b100011 4
1#
1'
#2412
0'
#2418
0!
0#
1'
#2424
0'
#2430
b100100 4
1#
1'
#2436
0'
#2442
1!
0#
1'
#2448
0'
#2454
b100101 4
1#
1'
#2460
0'
#2466
0!
0#
1'
#2472
0'
#2478
b100110 4
1#
1'
#2484
0'
#2490
1!
0#
1'
#2496
0'
#2502
b100111 4
1#
1'
#2508
0'
#2514
0!
0#
1'
#2520
0'
#2526
b101000 4
1#
1'
#2532
0'
#2538
1?
b1100100 @
0;
08
0#
1'
#2544
0'
#2550
b1100011 @
1"
z!
1'
#2556
0'
#2562
b1100010 @
1'
#2568
0'
#2574
b1100001 @
1'
#2580
0'
#2586
b1100000 @
1'
#2592
0'
#2598
b1011111 @
1'
#2604
0'
#2610
b1011110 @
1'
#2616
0'
#2622
b1011101 @
1'
#2628
0'
#2634
b1011100 @
1'
#2640
0'
#2646
b1011011 @
1'
#2652
0'
#2658
b1011010 @
1'
#2664
0'
#2670
b1011001 @
1'
#2676
0'
#2682
b1011000 @
1'
#2688
0'
#2694
b1010111 @
1'
#2700
0'
#2706
b1010110 @
1'
#2712
0'
#2718
b1010101 @
1'
#2724
0'
#2730
b1010100 @
1'
#2736
0'
#2742
b1010011 @
1'
#2748
0'
#2754
b1010010 @
1'
#2760
0'
#2766
b1010001 @
1'
#2772
0'
#2778
b1010000 @
1'
#2784
0'
#2790
b1001111 @
1'
#2796
0'
#2802
b1001110 @
1'
#2808
0'
#2814
b1001101 @
1'
#2820
0'
#2826
b1001100 @
1'
#2832
0'
#2838
b1001011 @
1'
#2844
0'
#2850
b1001010 @
1'
#2856
0'
#2862
b1001001 @
1'
#2868
0'
#2874
b1001000 @
1'
#2880
0'
#2886
b1000111 @
1'
#2892
0'
#2898
b1000110 @
1'
#2904
0'
#2910
b1000101 @
1'
#2916
0'
#2922
b1000100 @
1'
#2928
0'
#2934
b1000011 @
1'
#2940
0'
#2946
b1000010 @
1'
#2952
0'
#2958
b1000001 @
1'
#2964
0'
#2970
b1000000 @
1'
#2976
0'
#2982
b111111 @
1'
#2988
0'
#2994
b111110 @
1'
#3000
0'
#3006
b111101 @
1'
#3012
0'
#3018
b111100 @
1'
#3024
0'
#3030
b111011 @
1'
#3036
0'
#3042
b111010 @
1'
#3048
0'
#3054
b111001 @
1'
#3060
0'
#3066
b111000 @
1'
#3072
0'
#3078
b110111 @
1'
#3084
0'
#3090
b110110 @
1'
#3096
0'
#3102
b110101 @
1'
#3108
0'
#3114
b110100 @
1'
#3120
0'
#3126
b110011 @
1'
#3132
0'
#3138
b110010 @
1'
#3144
0'
#3150
b110001 @
1'
#3156
0'
#3162
b110000 @
1'
#3168
0'
#3174
b101111 @
1'
#3180
0'
#3186
b101110 @
1'
#3192
0'
#3198
b101101 @
1'
#3204
0'
#3210
b101100 @
1'
#3216
0'
#3222
b101011 @
1'
#3228
0'
#3234
b101010 @
1'
#3240
0'
#3246
b101001 @
1'
#3252
0'
#3258
b101000 @
1'
#3264
0'
#3270
b100111 @
1'
#3276
0'
#3282
b100110 @
1'
#3288
0'
#3294
b100101 @
1'
#3300
0'
#3306
b100100 @
1'
#3312
0'
#3318
b100011 @
1'
#3324
0'
#3330
b100010 @
1'
#3336
0'
#3342
b100001 @
1'
#3348
0'
#3354
b100000 @
1'
#3360
0'
#3366
b11111 @
1'
#3372
0'
#3378
b11110 @
1'
#3384
0'
#3390
b11101 @
1'
#3396
0'
#3402
b11100 @
1'
#3408
0'
#3414
b11011 @
1'
#3420
0'
#3426
b11010 @
1'
#3432
0'
#3438
b11001 @
1'
#3444
0'
#3450
b11000 @
1'
#3456
0'
#3462
b10111 @
1'
#3468
0'
#3474
b10110 @
1'
#3480
0'
#3486
b10101 @
1'
#3492
0'
#3498
b10100 @
1'
#3504
0'
#3510
b10011 @
1'
#3516
0'
#3522
b10010 @
1'
#3528
0'
#3534
b10001 @
1'
#3540
0'
#3546
b10000 @
1'
#3552
0'
#3558
b1111 @
1'
#3564
0'
#3570
b1110 @
1'
#3576
0'
#3582
b1101 @
1'
#3588
0'
#3594
b1100 @
1'
#3600
0'
#3606
b1011 @
1'
#3612
0'
#3618
b1010 @
1'
#3624
0'
#3630
b1001 @
1'
#3636
0'
#3642
b1000 @
1'
#3648
0'
#3654
b111 @
1'
#3660
0'
#3666
b110 @
1'
#3672
0'
#3678
b101 @
1'
#3684
0'
#3690
b100 @
1'
#3696
0'
#3702
b11 @
1'
#3708
0'
#3714
b10 @
1'
#3720
0'
#3726
b1 @
1'
#3732
0'
#3738
b0 @
1'
#3744
0'
#3750
0?
1'
