EClockDelay.v
module e_clk_delay (
    input i_clk,          // Fast PLL clock (e.g., 100 MHz)
    input i_e_clk,        // 6809 E clock
    output reg o_e_longdelay = 0,  // Active-low buffer OE (initialized to disabled)
    output reg o_e_shortdelay = 0  // Active-low buffer OE (initialized to disabled)
);

    reg e_prev = 1;
    reg [2:0] counter = 0; // Increased to 3 bits to accommodate larger delay
    reg delaying = 0;
    reg [6:0] start_counter = 0; // 6-bit counter for delay

    always @(posedge i_clk) begin
        e_prev <= i_e_clk;

        // While E is high, keep output enable active (1)
        if (i_e_clk) begin
            delaying <= 0;
            counter <= 0;
            o_e_longdelay <= 1;
           
            if (start_counter < 6'd44) begin
                o_e_shortdelay <= 0; // Enable short delay buffer
                start_counter <= start_counter + 1;
            end else begin
                o_e_shortdelay <= 1; // Disable short delay buffer
            end
            

        end
        // On falling edge of E, start delay
        else if (e_prev && ~i_e_clk) begin
            delaying <= 1;
            counter <= 3'd4; // 4 cycles delay (40ns @ 100MHz)
            o_e_longdelay <= 1;
            o_e_shortdelay <= 1;

        end
        // Finish delay after falling edge
        else if (delaying) begin
            if (counter == 0) begin
                o_e_longdelay <= 0; // Disable buffer (OE low = inactive)
                o_e_shortdelay <= 0; // Disable buffer (OE low = inactive)
                delaying <= 0;
            end else begin
                counter <= counter - 1;
                o_e_longdelay <= 1; // Still active during delay
                o_e_shortdelay <= 1;
            end
        end
        // Default state when idle and not delaying
        else begin
            o_e_longdelay <= 0;
            o_e_shortdelay <= 0;
            start_counter <= 0; // Reset start counter
        end
    end

endmodule

TB_EClockDelay.v
`timescale 1ns / 1ps

module EClockDelayTB;

    // Inputs
    reg i_clk;          // Fast PLL clock (e.g., 100 MHz)
    reg i_e_clk;        // 6809 E clock

    // Outputs
    wire o_e_shortdelay;  // Short delay output

    // Instantiate the Unit Under Test (UUT)
    e_clk_delay uut (
        .i_clk(i_clk),
        .i_e_clk(i_e_clk),
        .o_e_shortdelay(o_e_shortdelay)
    );

    // Clock generation for i_clk (100 MHz)
    initial begin
        i_clk = 0;
        forever #5 i_clk = ~i_clk; // 10ns clock period (100 MHz)
    end

    // Test procedure
    initial begin
        $dumpfile("simulation.vcd");
        $dumpvars(0, EClockDelayTB);

        // Initialize inputs
        i_e_clk = 0;

        // Wait for reset
        #20;

        // Simulate E clock signal (6809 E clock)
        i_e_clk = 1; #500;  // E clock high for 500ns
        i_e_clk = 0; #500;  // E clock low for 500ns
        i_e_clk = 1; #1500;  // E clock high for 500ns
        i_e_clk = 0; #500;  // E clock low for 500ns
        i_e_clk = 1; #500;  // E clock high for 500ns
        i_e_clk = 0; #500;  // E clock low for 500ns

        // End simulation
        #500;
        $finish;
    end

    // Monitor signals for debugging
    initial begin
        $monitor("Time: %0dns, i_clk: %b, i_e_clk: %b, o_e_longdelay: %b, o_e_shortdelay: %b",
                 $time, i_clk, i_e_clk, o_e_longdelay, o_e_shortdelay);
    end

endmodule

simulation.vcd
$date
	Thu Apr 17 15:18:44 2025
$end
$version
	Icarus Verilog
$end
$timescale
	1ps
$end
$scope module EClockDelayTB $end
$var wire 1 ! o_e_shortdelay $end
$var wire 1 " o_e_longdelay $end
$var reg 1 # i_clk $end
$var reg 1 $ i_e_clk $end
$scope module uut $end
$var wire 1 # i_clk $end
$var wire 1 $ i_e_clk $end
$var reg 3 % counter [2:0] $end
$var reg 1 & delaying $end
$var reg 1 ' e_prev $end
$var reg 1 " o_e_longdelay $end
$var reg 1 ! o_e_shortdelay $end
$var reg 7 ( start_counter [6:0] $end
$upscope $end
$upscope $end
$enddefinitions $end
#0
$dumpvars
b0 (
1'
0&
b0 %
0$
0#
0"
0!
$end
#5000
1!
1"
b100 %
1&
0'
1#
#10000
0#
#15000
b11 %
1#
#20000
0#
1$
#25000
b1 (
0!
b0 %
0&
1'
1#
#30000
0#
#35000
b10 (
1#
#40000
0#
#45000
b11 (
1#
#50000
0#
#55000
b100 (
1#
#60000
0#
#65000
b101 (
1#
#70000
0#
#75000
b110 (
1#
#80000
0#
#85000
b111 (
1#
#90000
0#
#95000
b1000 (
1#
#100000
0#
#105000
b1001 (
1#
#110000
0#
#115000
b1010 (
1#
#120000
0#
#125000
b1011 (
1#
#130000
0#
#135000
b1100 (
1#
#140000
0#
#145000
b1101 (
1#
#150000
0#
#155000
b1110 (
1#
#160000
0#
#165000
b1111 (
1#
#170000
0#
#175000
b10000 (
1#
#180000
0#
#185000
b10001 (
1#
#190000
0#
#195000
b10010 (
1#
#200000
0#
#205000
b10011 (
1#
#210000
0#
#215000
b10100 (
1#
#220000
0#
#225000
b10101 (
1#
#230000
0#
#235000
b10110 (
1#
#240000
0#
#245000
b10111 (
1#
#250000
0#
#255000
b11000 (
1#
#260000
0#
#265000
b11001 (
1#
#270000
0#
#275000
b11010 (
1#
#280000
0#
#285000
b11011 (
1#
#290000
0#
#295000
b11100 (
1#
#300000
0#
#305000
b11101 (
1#
#310000
0#
#315000
b11110 (
1#
#320000
0#
#325000
b11111 (
1#
#330000
0#
#335000
b100000 (
1#
#340000
0#
#345000
b100001 (
1#
#350000
0#
#355000
b100010 (
1#
#360000
0#
#365000
b100011 (
1#
#370000
0#
#375000
b100100 (
1#
#380000
0#
#385000
b100101 (
1#
#390000
0#
#395000
b100110 (
1#
#400000
0#
#405000
b100111 (
1#
#410000
0#
#415000
b101000 (
1#
#420000
0#
#425000
b101001 (
1#
#430000
0#
#435000
b101010 (
1#
#440000
0#
#445000
b101011 (
1#
#450000
0#
#455000
b101100 (
1#
#460000
0#
#465000
1!
1#
#470000
0#
#475000
1#
#480000
0#
#485000
1#
#490000
0#
#495000
1#
#500000
0#
#505000
1#
#510000
0#
#515000
1#
#520000
0#
0$
#525000
b100 %
1&
0'
1#
#530000
0#
#535000
b11 %
1#
#540000
0#
#545000
b10 %
1#
#550000
0#
#555000
b1 %
1#
#560000
0#
#565000
b0 %
1#
#570000
0#
#575000
0&
0!
0"
1#
#580000
0#
#585000
b0 (
1#
