FlashSpi.v
// SPI device uses SPI Mode 0, with active low Chip Select
// Max speed rating of SPI Flash with read instruction is 50MHz. 
module spi_flash_controller (
    input spi_ce,            // SPI chip select signal from address decoder
    input reset,             // Reset signal
    input i_enable,
    input [15:0] i_ADDRESS_BUS, // Address from 6809 (16 bits)
    input [7:0] i_DataBus,  // Data input from 6809
    input i_RW,               // Read/Write control signal (only reads for flash)
    input clk,                // System clock
    input i_SPI_MISO,         // SPI Master In Slave Out
    output reg o_SPI_CLK,     // SPI Clock
    output reg o_SPI_MOSI,    // SPI Master Out Slave In
    output reg o_SPI_CS,      // SPI Chip Select (active low)
    output reg [7:0] o_spi_data,  // Data output to 6809
    output reg o_MemoryReady,
    output reg o_HALT,
    output reg [7:0] spi_datawrite          // Data to write to SPI flash
);

    wire [7:0] spi_read_command = 8'h03; // Command for SPI flash (READ command is 0x03)
    wire [7:0] spi_page_command = 8'h02; // Command for SPI flash (WRITE PAGE command is 0x02)
    wire [7:0] spi_write_enable_command = 8'h06; // Command for SPI flash (WRITE ENABLE command is 0x06)
    reg [23:0] spi_readaddress = 24'b0; // Address for SPI flash (24 bits)
    reg [23:0] spi_writeaddress = 24'b0; // Address for SPI flash (24 bits)
    reg [5:0] bit_counter = 6'd0;     // Tracks SPI transaction progress (6 bits to cover up to 40)
    reg [15:0] writedelay_counter = 0;
    reg spi_read_active = 0;               // Indicates SPI read operation is active
    reg spi_write_active = 0;               // Indicates SPI write enable operation is active
    reg start_write_delay = 0;
    reg spi_page_active = 0;               // Indicates SPI page operation is active
    reg clock_delay = 0;
    reg start_write = 0;
    reg start_read = 0;
    // SPI flash controller logic
    // Reset logic

    always @(negedge i_enable) begin
        if (!i_RW && spi_ce && !spi_write_active) begin
            spi_writeaddress <= {12'b0, i_ADDRESS_BUS[11:0]}; // Lower 12 bits of address to 24-bit SPI address
            start_write <= 1'b1;
            spi_datawrite <= i_DataBus;
        end
        else begin
            start_write <= 1'b0;
        end
    end

    always @(posedge i_enable) begin
        if (i_RW && spi_ce && !spi_read_active) begin
            spi_readaddress <= {12'b0, i_ADDRESS_BUS[11:0]}; // Lower 12 bits of address to 24-bit SPI address
            start_read <= 1'b1;
        end
        else begin
            start_read <= 1'b0;
        end
    end


    always @(posedge clk) begin
        if (~reset) begin
            o_spi_data <= 8'b0;          // Reset data
            bit_counter <= 6'b0;       // Reset bit counter
            spi_read_active <= 1'b0;        // Reset SPI read active flag
            spi_write_active <= 1'b0;        // Reset SPI write active flag
            spi_page_active <= 1'b0;        // Reset SPI page active flag
            o_MemoryReady <= 1'b1;    // Allow the 6809 to continue
            o_HALT <= 1'b1;         // Deactivate HALT signal
        end

        // Start SPI transaction when chip select is active and it's a read cycle
        if (start_read && reset) begin
            spi_read_active <= 1'b1;         // Mark SPI as active
            bit_counter <= 6'd0;        // Reset bit counter
            clock_delay <= 1'b0;
       end
       if (start_write && !spi_write_active && !spi_page_active && !spi_read_active && reset) begin
            spi_write_active <= 1'b1;         // Mark write enable as active
            spi_page_active <= 1'b0;         // Mark page as inactive
            bit_counter <= 6'd0;        // Reset bit counter
            clock_delay <= 1'b0;
        end

        
        // Read data from SPI flash
        if (spi_read_active && reset) begin
            if(spi_write_active || start_write_delay) begin
               o_HALT <= 1'b0;         // Activate HALT signal
            end
            else begin
                o_HALT <= 1'b1;         // Deactivate HALT signal
                o_SPI_CS <= 1'b0;           // Activate SPI chip select
                o_MemoryReady <= 1'b0;     // Keep 6809 in wait state during SPI transaction

                if (clock_delay) begin 
                    o_SPI_CLK = ~o_SPI_CLK;   // Toggle SPI clock
                end
                clock_delay <= 1'b1;

                if (~o_SPI_CLK) begin
                    // On rising edge of SPI clock, handle data transfer
                    if (bit_counter < 6'd8) begin //7
                        // Send SPI command (8 bits)
                        o_SPI_MOSI <= spi_read_command[7 - bit_counter];
                    end else if (bit_counter < 6'd32) begin
                        // Send 24-bit SPI address (address starts at bit 8)
                        o_SPI_MOSI <= spi_readaddress[31 - bit_counter];
                    end else if (bit_counter == 6'd40) begin
                        // End of SPI transaction
                        spi_read_active <= 1'b0;      // Mark SPI as inactive
                        o_MemoryReady <= 1'b1;     // Allow the 6809 to continue
                    end
                end
                else begin
                    if (bit_counter < 6'd40) begin
                        // Receive 8-bit data (after address)
                        o_spi_data[7 - (bit_counter - 6'd32)] <= i_SPI_MISO;
                    end
                    // Increment bit counter (always within 6-bit range, safe to truncate)
                    bit_counter <= bit_counter + 1;
                end
            end
        end 
        // Enable Write data to SPI flash
        if (spi_write_active && !spi_page_active && reset) begin
            o_SPI_CS <= 1'b0;           // Activate SPI chip select
            if (clock_delay) begin 
                o_SPI_CLK = ~o_SPI_CLK;   // Toggle SPI clock
            end
            clock_delay <= 1'b1;

            if (~o_SPI_CLK) begin
                // On rising edge of SPI clock, handle data transfer
                if (bit_counter < 6'd8) begin //7
                    // Send SPI command (8 bits)
                    o_SPI_MOSI <= spi_write_enable_command[7 - bit_counter];
                end  
            end
            else begin
                if (bit_counter == 6'd8) begin
                    // End of SPI transaction
                    spi_page_active <= 1'b1;      // Mark SPI page active
                    bit_counter <= 6'd0;        // Reset bit counter
                    clock_delay <= 1'b0;
                    o_SPI_CS <= 1'b1;           // Deactivate SPI chip select
                    o_SPI_CLK <= 1'b0;         // Clock low in idle (for SPI Mode 0)
                end
                // Increment bit counter (always within 6-bit range, safe to truncate)
                else begin
                bit_counter <= bit_counter + 1;
                end
            end
        end
        // Write data to SPI flash
        if (spi_page_active && reset) begin
            o_SPI_CS <= 1'b0;           // Activate SPI chip select
           
            if (clock_delay) begin 
                o_SPI_CLK = ~o_SPI_CLK;   // Toggle SPI clock
            end
            clock_delay <= 1'b1;

            if (~o_SPI_CLK) begin
                // On rising edge of SPI clock, handle data transfer
                if (bit_counter < 6'd8) begin //7
                    // Send SPI command (8 bits)
                    o_SPI_MOSI <= spi_page_command[7 - bit_counter];
                end else if (bit_counter < 6'd32) begin
                    // Send 24-bit SPI address (address starts at bit 8)
                    o_SPI_MOSI <= spi_writeaddress[31 - bit_counter];

                end
                else if (bit_counter < 6'd40) begin
                // Receive 8-bit data (after address)
                o_SPI_MOSI <= spi_datawrite[7 - (bit_counter - 6'd32)];
                end    
                else if (bit_counter == 6'd40) begin
                    // End of SPI transaction
                    spi_page_active <= 1'b0;      // Mark SPI as inactive
                    spi_write_active <= 1'b0;      // Delay finished for write. 
                    writedelay_counter <= 16'd100;  // Set counter for 6ms @ 8MHz max time for write on a 25LC1024 eeprom, changed to 48000 to 100 for test.
                    start_write_delay <= 1'b1;
                    o_SPI_CS <= 1'b0;           // Activate SPI chip select
                end
            end
            else begin
                // Increment bit counter (always within 6-bit range, safe to truncate)
                bit_counter <= bit_counter + 1;
            end
        end 
        if(!spi_read_active && !spi_write_active) begin
            // Idle state: set SPI signals to default
            o_SPI_MOSI <= 1'bz;        // High Impedance at idle
            o_SPI_CLK <= 1'b0;         // Clock low in idle (for SPI Mode 0)
            o_MemoryReady <= 1'b1;     // Allow the 6809 to continue
            o_SPI_CS <= 1'b1;        // Deactivate SPI chip select
        end
        if(start_write_delay) begin
                if (writedelay_counter > 0) begin
                writedelay_counter <= writedelay_counter - 1; // count down to zero for delay
                end 
                else begin
                    start_write_delay <= 1'b0;
                end
        end
    end
endmodule

TB_FlashSpi.v
`timescale 1ns / 1ns
module tb_spi_flash_controller;

    reg spi_ce;
    reg reset;
    reg [15:0] i_ADDRESS_BUS;
    reg [7:0] i_DataBus;
    reg i_RW;
    reg clk;
    reg i_SPI_MISO;
    reg i_enable; // Change from wire to reg
    wire o_SPI_CLK;
    wire o_SPI_MOSI;
    wire o_SPI_CS;
    wire [7:0] o_DATA;
    wire o_MemoryReady;
    wire o_HALT;

    // Instantiate the Unit Under Test (UUT)
    spi_flash_controller uut (
        .spi_ce(spi_ce),
        .reset(reset),
        .i_enable(i_enable),
        .i_ADDRESS_BUS(i_ADDRESS_BUS),
        .i_DataBus(i_DataBus),
        .i_RW(i_RW),
        .clk(clk),
        .i_SPI_MISO(i_SPI_MISO),
        .o_SPI_CLK(o_SPI_CLK),
        .o_SPI_MOSI(o_SPI_MOSI),
        .o_SPI_CS(o_SPI_CS),
        .o_spi_data(o_DATA),
        .o_MemoryReady(o_MemoryReady),
        .o_HALT(o_HALT)
    );

    // Clock generation at 88.67 MHz 
    localparam CLOCK_PERIOD_NS = 11.285; // 88.67 MHz 
    initial clk = 0;
    initial i_enable = 0;
    always #(CLOCK_PERIOD_NS / 2) clk = ~clk;
    always #(CLOCK_PERIOD_NS) i_enable = ~i_enable;

    // Simulation task for SPI flash read operation
    task spi_flash_read(input [15:0] address);
        begin
            #24;
            spi_ce = 1;
            i_ADDRESS_BUS = address;
            i_RW = 1;  // Read operation   
            #24       
            spi_ce = 0;
            #774;  // Wait for SPI operation to begin
            #24 i_SPI_MISO = 1;
            #24 i_SPI_MISO = 1;
            #24 i_SPI_MISO = 1;
            #24 i_SPI_MISO = 1;
            #24 i_SPI_MISO = 1;
            #24 i_SPI_MISO = 0;
            #24 i_SPI_MISO = 1;
            #24 i_SPI_MISO = 0;
        end
    endtask
    task spi_flash_reread(input [15:0] address);
    begin
            spi_ce = 1;
            i_ADDRESS_BUS = address;
            i_RW = 1;  // Read operation
            #24
            spi_ce = 0;   
            #774;  // Wait for SPI operation to begin
            #24 i_SPI_MISO = 1;
            #24 i_SPI_MISO = 1;
            #24 i_SPI_MISO = 1;
            #24 i_SPI_MISO = 1;
            #24 i_SPI_MISO = 1;
            #24 i_SPI_MISO = 0;
            #24 i_SPI_MISO = 1;
            #24 i_SPI_MISO = 0;
        end
    endtask
    // Simulation task for SPI flash read operation
    task spi_flash_write(input [15:0] address, input [7:0] databus);
        begin
            #24;
            #24;
            #24;
            #24;
            #24;
            #24;
            i_RW = 0;
            spi_ce = 1;
            #24;
            i_ADDRESS_BUS = address;
            i_DataBus = databus;
            spi_ce = 0;
            i_RW = 1;
        end
    endtask

    initial begin
        $dumpfile("simulation.vcd");
        $dumpvars(0, tb_spi_flash_controller);
        //Initialize Inputs
        spi_ce = 0;
        i_ADDRESS_BUS = 16'h0000;
        i_RW = 1;
        reset = 1;
        #10;
        reset = 0;
        #10;
        reset = 1;
        i_DataBus = 8'h00; // Default value to prevent high-Z
        //Reset SPI Controller signals
        #100;
        //Stimulate SPI flash read for address 0x1234
        spi_flash_read(16'h3AAA);
        #100;  // Return to idle state after operation
        $display("Final SPI Data Received: %h", o_DATA);
        //Initialize Inputs
        spi_flash_write(16'h3000, 8'hAA);
        #800;  // Wait for SPI operation to begin
        spi_flash_reread(16'h3AAA);
        #2550;  // Wait for SPI operation to begin
        $finish;
    end
endmodule

simulation.vcd
$date
	Thu May 29 22:00:49 2025
$end
$version
	Icarus Verilog
$end
$timescale
	1ns
$end
$scope module tb_spi_flash_controller $end
$var wire 1 ! o_SPI_MOSI $end
$var wire 1 " o_SPI_CS $end
$var wire 1 # o_SPI_CLK $end
$var wire 1 $ o_MemoryReady $end
$var wire 1 % o_HALT $end
$var wire 8 & o_DATA [7:0] $end
$var reg 1 ' clk $end
$var reg 16 ( i_ADDRESS_BUS [15:0] $end
$var reg 8 ) i_DataBus [7:0] $end
$var reg 1 * i_RW $end
$var reg 1 + i_SPI_MISO $end
$var reg 1 , i_enable $end
$var reg 1 - reset $end
$var reg 1 . spi_ce $end
$scope module uut $end
$var wire 1 ' clk $end
$var wire 16 / i_ADDRESS_BUS [15:0] $end
$var wire 8 0 i_DataBus [7:0] $end
$var wire 1 * i_RW $end
$var wire 1 + i_SPI_MISO $end
$var wire 1 , i_enable $end
$var wire 1 - reset $end
$var wire 1 . spi_ce $end
$var wire 8 1 spi_page_command [7:0] $end
$var wire 8 2 spi_read_command [7:0] $end
$var wire 8 3 spi_write_enable_command [7:0] $end
$var reg 6 4 bit_counter [5:0] $end
$var reg 1 5 clock_delay $end
$var reg 1 % o_HALT $end
$var reg 1 $ o_MemoryReady $end
$var reg 1 # o_SPI_CLK $end
$var reg 1 " o_SPI_CS $end
$var reg 1 ! o_SPI_MOSI $end
$var reg 8 6 o_spi_data [7:0] $end
$var reg 8 7 spi_datawrite [7:0] $end
$var reg 1 8 spi_page_active $end
$var reg 1 9 spi_read_active $end
$var reg 24 : spi_readaddress [23:0] $end
$var reg 1 ; spi_write_active $end
$var reg 24 < spi_writeaddress [23:0] $end
$var reg 1 = start_read $end
$var reg 1 > start_write $end
$var reg 1 ? start_write_delay $end
$var reg 16 @ writedelay_counter [15:0] $end
$upscope $end
$scope task spi_flash_read $end
$var reg 16 A address [15:0] $end
$upscope $end
$scope task spi_flash_reread $end
$var reg 16 B address [15:0] $end
$upscope $end
$scope task spi_flash_write $end
$var reg 16 C address [15:0] $end
$var reg 8 D databus [7:0] $end
$upscope $end
$upscope $end
$enddefinitions $end
#0
$dumpvars
bx D
bx C
bx B
bx A
b0 @
0?
0>
0=
b0 <
0;
b0 :
09
08
bx 7
bx 6
05
b0 4
b110 3
b11 2
b10 1
bx 0
b0 /
0.
1-
0,
x+
1*
bx )
b0 (
0'
bx &
x%
x$
x#
x"
x!
$end
#6
1"
1$
0#
z!
1'
#10
0-
#11
1,
#12
0'
#18
1%
b0 &
b0 6
1'
#20
b0 )
b0 0
1-
#22
0,
#24
0'
#30
1'
#33
1,
#36
0'
#42
1'
#44
0,
#48
0'
#54
1'
#55
1,
#60
0'
#66
1'
0,
#72
0'
#77
1,
#78
1'
#84
0'
#88
0,
#90
1'
#96
0'
#99
1,
#102
1'
#108
0'
#110
0,
#114
1'
#120
0'
b11101010101010 A
#121
1,
#126
1'
#132
0'
0,
#138
1'
#143
1,
#144
0'
b11101010101010 (
b11101010101010 /
1.
#150
1'
#154
0,
#156
0'
#162
1'
#165
1=
b101010101010 :
1,
#168
0'
0.
#174
19
1'
#176
0,
#180
0'
#186
0!
15
0$
0"
1'
#187
0=
1,
#192
0'
#198
b1 4
1#
1'
0,
#204
0'
#209
1,
#210
0#
1'
#216
0'
#220
0,
#222
b10 4
1#
1'
#228
0'
#231
1,
#234
0#
1'
#240
0'
#242
0,
#246
b11 4
1#
1'
#252
0'
#253
1,
#258
0#
1'
#264
0'
0,
#270
b100 4
1#
1'
#275
1,
#276
0'
#282
0#
1'
#286
0,
#288
0'
#294
b101 4
1#
1'
#297
1,
#300
0'
#306
0#
1'
#308
0,
#312
0'
#318
b110 4
1#
1'
#319
1,
#324
0'
#330
1!
0#
1'
0,
#336
0'
#341
1,
#342
b111 4
1#
1'
#348
0'
#352
0,
#354
0#
1'
#360
0'
#363
1,
#366
b1000 4
1#
1'
#372
0'
#374
0,
#378
0!
0#
1'
#384
0'
#385
1,
#390
b1001 4
1#
1'
#396
0'
0,
#402
0#
1'
#407
1,
#408
0'
#414
b1010 4
1#
1'
#418
0,
#420
0'
#426
0#
1'
#429
1,
#432
0'
#438
b1011 4
1#
1'
#440
0,
#444
0'
#450
0#
1'
#451
1,
#456
0'
#462
b1100 4
1#
1'
0,
#468
0'
#473
1,
#474
0#
1'
#480
0'
#484
0,
#486
b1101 4
1#
1'
#492
0'
#495
1,
#498
0#
1'
#504
0'
#506
0,
#510
b1110 4
1#
1'
#516
0'
#517
1,
#522
0#
1'
#528
0'
0,
#534
b1111 4
1#
1'
#539
1,
#540
0'
#546
0#
1'
#550
0,
#552
0'
#558
b10000 4
1#
1'
#561
1,
#564
0'
#570
0#
1'
#572
0,
#576
0'
#582
b10001 4
1#
1'
#583
1,
#588
0'
#594
0#
1'
0,
#600
0'
#605
1,
#606
b10010 4
1#
1'
#612
0'
#616
0,
#618
0#
1'
#624
0'
#627
1,
#630
b10011 4
1#
1'
#636
0'
#638
0,
#642
0#
1'
#648
0'
#649
1,
#654
b10100 4
1#
1'
#660
0'
0,
#666
1!
0#
1'
#671
1,
#672
0'
#678
b10101 4
1#
1'
#682
0,
#684
0'
#690
0!
0#
1'
#693
1,
#696
0'
#702
b10110 4
1#
1'
#704
0,
#708
0'
#714
1!
0#
1'
#715
1,
#720
0'
#726
b10111 4
1#
1'
0,
#732
0'
#737
1,
#738
0!
0#
1'
#744
0'
#748
0,
#750
b11000 4
1#
1'
#756
0'
#759
1,
#762
1!
0#
1'
#768
0'
#770
0,
#774
b11001 4
1#
1'
#780
0'
#781
1,
#786
0!
0#
1'
#792
0'
0,
#798
b11010 4
1#
1'
#803
1,
#804
0'
#810
1!
0#
1'
#814
0,
#816
0'
#822
b11011 4
1#
1'
#825
1,
#828
0'
#834
0!
0#
1'
#836
0,
#840
0'
#846
b11100 4
1#
1'
#847
1,
#852
0'
#858
1!
0#
1'
0,
#864
0'
#869
1,
#870
b11101 4
1#
1'
#876
0'
#880
0,
#882
0!
0#
1'
#888
0'
#891
1,
#894
b11110 4
1#
1'
#900
0'
#902
0,
#906
1!
0#
1'
#912
0'
#913
1,
#918
b11111 4
1#
1'
#924
0'
0,
#930
0!
0#
1'
#935
1,
#936
0'
#942
b100000 4
1#
1'
#946
0,
#948
0'
#954
0#
1'
#957
1,
#960
0'
#966
b100001 4
b10000000 &
b10000000 6
1#
1'
1+
#968
0,
#972
0'
#978
0#
1'
#979
1,
#984
0'
#990
b100010 4
b11000000 &
b11000000 6
1#
1'
0,
#996
0'
#1001
1,
#1002
0#
1'
#1008
0'
#1012
0,
#1014
b100011 4
b11100000 &
b11100000 6
1#
1'
#1020
0'
#1023
1,
#1026
0#
1'
#1032
0'
#1034
0,
#1038
b100100 4
b11110000 &
b11110000 6
1#
1'
#1044
0'
#1045
1,
#1050
0#
1'
#1056
0'
0,
#1062
b100101 4
b11111000 &
b11111000 6
1#
1'
#1067
1,
#1068
0'
#1074
0#
1'
#1078
0,
#1080
0'
#1086
b100110 4
1#
1'
0+
#1089
1,
#1092
0'
#1098
0#
1'
#1100
0,
#1104
0'
#1110
b100111 4
b11111010 &
b11111010 6
1#
1'
1+
#1111
1,
#1116
0'
#1122
0#
1'
0,
#1128
0'
#1133
1,
#1134
b101000 4
1#
1'
0+
#1140
0'
#1144
0,
#1146
1$
09
0#
1'
#1152
0'
#1155
1,
#1158
1"
z!
1'
#1164
0'
#1166
0,
#1170
1'
#1176
0'
#1177
1,
#1182
1'
#1188
0'
0,
#1194
1'
#1199
1,
#1200
0'
#1206
1'
#1210
0,
#1212
0'
#1218
1'
#1221
1,
#1224
0'
#1230
1'
#1232
0,
#1234
b10101010 D
b11000000000000 C
#1236
0'
#1242
1'
#1243
1,
#1248
0'
#1254
1'
0,
#1260
0'
#1265
1,
#1266
1'
#1272
0'
#1276
0,
#1278
1'
#1284
0'
#1287
1,
#1290
1'
#1296
0'
#1298
0,
#1302
1'
#1308
0'
#1309
1,
#1314
1'
#1320
0'
0,
#1326
1'
#1331
1,
#1332
0'
#1338
1'
#1342
0,
#1344
0'
#1350
1'
#1353
1,
#1356
0'
#1362
1'
#1364
0,
#1368
0'
#1374
1'
#1375
1,
#1378
1.
0*
#1380
0'
#1386
b0 7
1>
b101010101010 <
1'
0,
#1392
0'
#1397
1,
#1398
05
b0 4
1;
1'
#1402
1*
0.
b10101010 )
b10101010 0
b11000000000000 (
b11000000000000 /
#1404
0'
#1408
0>
0,
#1410
0!
15
0"
1'
#1416
0'
#1419
1,
#1422
b1 4
1#
1'
#1428
0'
#1430
0,
#1434
0#
1'
#1440
0'
#1441
1,
#1446
b10 4
1#
1'
#1452
0'
0,
#1458
0#
1'
#1463
1,
#1464
0'
#1470
b11 4
1#
1'
#1474
0,
#1476
0'
#1482
0#
1'
#1485
1,
#1488
0'
#1494
b100 4
1#
1'
#1496
0,
#1500
0'
#1506
0#
1'
#1507
1,
#1512
0'
#1518
b101 4
1#
1'
0,
#1524
0'
#1529
1,
#1530
1!
0#
1'
#1536
0'
#1540
0,
#1542
b110 4
1#
1'
#1548
0'
#1551
1,
#1554
0#
1'
#1560
0'
#1562
0,
#1566
b111 4
1#
1'
#1572
0'
#1573
1,
#1578
0!
0#
1'
#1584
0'
0,
#1590
b1000 4
1#
1'
#1595
1,
#1596
0'
#1602
0#
1'
#1606
0,
#1608
0'
#1614
1"
05
b0 4
18
0#
1'
#1617
1,
#1620
0'
#1626
15
0"
1'
#1628
0,
#1632
0'
#1638
b1 4
1#
1'
#1639
1,
#1644
0'
#1650
0#
1'
0,
#1656
0'
#1661
1,
#1662
b10 4
1#
1'
#1668
0'
#1672
0,
#1674
0#
1'
#1680
0'
#1683
1,
#1686
b11 4
1#
1'
#1692
0'
#1694
0,
#1698
0#
1'
#1704
0'
#1705
1,
#1710
b100 4
1#
1'
#1716
0'
0,
#1722
0#
1'
#1727
1,
#1728
0'
#1734
b101 4
1#
1'
#1738
0,
#1740
0'
#1746
0#
1'
#1749
1,
#1752
0'
#1758
b110 4
1#
1'
#1760
0,
#1764
0'
#1770
1!
0#
1'
#1771
1,
#1776
0'
#1782
b111 4
1#
1'
0,
#1788
0'
#1793
1,
#1794
0!
0#
1'
#1800
0'
#1804
0,
#1806
b1000 4
1#
1'
#1812
0'
#1815
1,
#1818
0#
1'
#1824
0'
#1826
0,
#1830
b1001 4
1#
1'
#1836
0'
#1837
1,
#1842
0#
1'
#1848
0'
0,
#1854
b1010 4
1#
1'
#1859
1,
#1860
0'
#1866
0#
1'
#1870
0,
#1872
0'
#1878
b1011 4
1#
1'
#1881
1,
#1884
0'
#1890
0#
1'
#1892
0,
#1896
0'
#1902
b1100 4
1#
1'
#1903
1,
#1908
0'
#1914
0#
1'
0,
#1920
0'
#1925
1,
#1926
b1101 4
1#
1'
#1932
0'
#1936
0,
#1938
0#
1'
#1944
0'
#1947
1,
#1950
b1110 4
1#
1'
#1956
0'
#1958
0,
#1962
0#
1'
#1968
0'
#1969
1,
#1974
b1111 4
1#
1'
#1980
0'
0,
#1986
0#
1'
#1991
1,
#1992
0'
#1998
b10000 4
1#
1'
#2002
0,
#2004
0'
#2010
0#
1'
#2013
1,
#2016
0'
#2022
b10001 4
1#
1'
#2024
0,
#2028
0'
#2034
0#
1'
#2035
1,
#2040
0'
#2046
b10010 4
1#
1'
0,
#2052
0'
#2057
1,
#2058
0#
1'
#2064
0'
#2068
0,
#2070
b10011 4
1#
1'
#2076
0'
#2079
1,
#2082
0#
1'
#2088
0'
#2090
0,
#2094
b10100 4
1#
1'
#2100
0'
#2101
1,
#2106
1!
0#
1'
#2112
0'
0,
#2118
b10101 4
1#
1'
#2123
1,
#2124
0'
#2130
0!
0#
1'
#2134
0,
#2136
0'
#2142
b10110 4
1#
1'
#2145
1,
#2148
0'
#2154
1!
0#
1'
#2156
0,
#2160
0'
#2166
b10111 4
1#
1'
#2167
1,
#2172
0'
#2178
0!
0#
1'
0,
#2184
0'
#2189
1,
#2190
b11000 4
1#
1'
#2196
0'
#2200
0,
#2202
1!
0#
1'
b11101010101010 (
b11101010101010 /
1.
b11101010101010 B
#2208
0'
#2211
1=
1,
#2214
15
b11001 4
19
1#
1'
#2220
0'
#2222
0,
#2226
0!
0%
15
b0 4
0#
1'
0.
#2232
0'
#2233
0=
1,
#2238
b1 4
1#
1'
#2244
0'
0,
#2250
0#
1'
#2255
1,
#2256
0'
#2262
b10 4
1#
1'
#2266
0,
#2268
0'
#2274
0#
1'
#2277
1,
#2280
0'
#2286
b11 4
1#
1'
#2288
0,
#2292
0'
#2298
0#
1'
#2299
1,
#2304
0'
#2310
b100 4
1#
1'
0,
#2316
0'
#2321
1,
#2322
0#
1'
#2328
0'
#2332
0,
#2334
b101 4
1#
1'
#2340
0'
#2343
1,
#2346
0#
1'
#2352
0'
#2354
0,
#2358
b110 4
1#
1'
#2364
0'
#2365
1,
#2370
1!
0#
1'
#2376
0'
0,
#2382
b111 4
1#
1'
#2387
1,
#2388
0'
#2394
0!
0#
1'
#2398
0,
#2400
0'
#2406
b1000 4
1#
1'
#2409
1,
#2412
0'
#2418
0#
1'
#2420
0,
#2424
0'
#2430
b1001 4
1#
1'
#2431
1,
#2436
0'
#2442
0#
1'
0,
#2448
0'
#2453
1,
#2454
b1010 4
1#
1'
#2460
0'
#2464
0,
#2466
0#
1'
#2472
0'
#2475
1,
#2478
b1011 4
1#
1'
#2484
0'
#2486
0,
#2490
0#
1'
#2496
0'
#2497
1,
#2502
b1100 4
1#
1'
#2508
0'
0,
#2514
0#
1'
#2519
1,
#2520
0'
#2526
b1101 4
1#
1'
#2530
0,
#2532
0'
#2538
0#
1'
#2541
1,
#2544
0'
#2550
b1110 4
1#
1'
#2552
0,
#2556
0'
#2562
0#
1'
#2563
1,
#2568
0'
#2574
b1111 4
1#
1'
0,
#2580
0'
#2585
1,
#2586
0#
1'
#2592
0'
#2596
0,
#2598
b10000 4
1#
1'
#2604
0'
#2607
1,
#2610
0#
1'
#2616
0'
#2618
0,
#2622
b10001 4
1#
1'
#2628
0'
#2629
1,
#2634
0#
1'
#2640
0'
0,
#2646
b10010 4
1#
1'
#2651
1,
#2652
0'
#2658
0#
1'
#2662
0,
#2664
0'
#2670
b10011 4
1#
1'
#2673
1,
#2676
0'
#2682
0#
1'
#2684
0,
#2688
0'
#2694
b10100 4
1#
1'
#2695
1,
#2700
0'
#2706
1!
0#
1'
0,
#2712
0'
#2717
1,
#2718
b10101 4
1#
1'
#2724
0'
#2728
0,
#2730
0!
0#
1'
#2736
0'
#2739
1,
#2742
b10110 4
1#
1'
#2748
0'
#2750
0,
#2754
1!
0#
1'
#2760
0'
#2761
1,
#2766
b10111 4
1#
1'
#2772
0'
0,
#2778
0!
0#
1'
#2783
1,
#2784
0'
#2790
b11000 4
1#
1'
#2794
0,
#2796
0'
#2802
1!
0#
1'
#2805
1,
#2808
0'
#2814
b11001 4
1#
1'
#2816
0,
#2820
0'
#2826
0!
0#
1'
#2827
1,
#2832
0'
#2838
b11010 4
1#
1'
0,
#2844
0'
#2849
1,
#2850
1!
0#
1'
#2856
0'
#2860
0,
#2862
b11011 4
1#
1'
#2868
0'
#2871
1,
#2874
0!
0#
1'
#2880
0'
#2882
0,
#2886
b11100 4
1#
1'
#2892
0'
#2893
1,
#2898
1!
0#
1'
#2904
0'
0,
#2910
b11101 4
1#
1'
#2915
1,
#2916
0'
#2922
0!
0#
1'
#2926
0,
#2928
0'
#2934
b11110 4
1#
1'
#2937
1,
#2940
0'
#2946
1!
0#
1'
#2948
0,
#2952
0'
#2958
b11111 4
1#
1'
#2959
1,
#2964
0'
#2970
0!
0#
1'
0,
#2976
0'
#2981
1,
#2982
b100000 4
1#
1'
#2988
0'
#2992
0,
#2994
0#
1'
#3000
0'
#3003
1,
#3006
b100001 4
1#
1'
#3012
0'
#3014
0,
#3018
0#
1'
#3024
0'
1+
#3025
1,
#3030
b100010 4
1#
1'
#3036
0'
0,
#3042
0#
1'
#3047
1,
#3048
0'
#3054
b100011 4
1#
1'
#3058
0,
#3060
0'
#3066
0#
1'
#3069
1,
#3072
0'
#3078
b100100 4
1#
1'
#3080
0,
#3084
0'
#3090
0#
1'
#3091
1,
#3096
0'
#3102
b100101 4
1#
1'
0,
#3108
0'
#3113
1,
#3114
0#
1'
#3120
0'
#3124
0,
#3126
b100110 4
1#
1'
#3132
0'
#3135
1,
#3138
0#
1'
#3144
0'
0+
#3146
0,
#3150
b100111 4
1#
1'
#3156
0'
#3157
1,
#3162
0#
1'
#3168
0'
0,
1+
#3174
b101000 4
1#
1'
#3179
1,
#3180
0'
#3186
1?
b1100100 @
0;
08
0#
1'
#3190
0,
#3192
0'
0+
#3198
b1100011 @
1'
#3201
1,
#3204
0'
#3210
b1100010 @
1'
#3212
0,
#3216
0'
#3222
b1100001 @
1'
#3223
1,
#3228
0'
#3234
b1100000 @
1'
0,
#3240
0'
#3245
1,
#3246
b1011111 @
1'
#3252
0'
#3256
0,
#3258
b1011110 @
1'
#3264
0'
#3267
1,
#3270
b1011101 @
1'
#3276
0'
#3278
0,
#3282
b1011100 @
1'
#3288
0'
#3289
1,
#3294
b1011011 @
1'
#3300
0'
0,
#3306
b1011010 @
1'
#3311
1,
#3312
0'
#3318
b1011001 @
1'
#3322
0,
#3324
0'
#3330
b1011000 @
1'
#3333
1,
#3336
0'
#3342
b1010111 @
1'
#3344
0,
#3348
0'
#3354
b1010110 @
1'
#3355
1,
#3360
0'
#3366
b1010101 @
1'
0,
#3372
0'
#3377
1,
#3378
b1010100 @
1'
#3384
0'
#3388
0,
#3390
b1010011 @
1'
#3396
0'
#3399
1,
#3402
b1010010 @
1'
#3408
0'
#3410
0,
#3414
b1010001 @
1'
#3420
0'
#3421
1,
#3426
b1010000 @
1'
#3432
0'
0,
#3438
b1001111 @
1'
#3443
1,
#3444
0'
#3450
b1001110 @
1'
#3454
0,
#3456
0'
#3462
b1001101 @
1'
#3465
1,
#3468
0'
#3474
b1001100 @
1'
#3476
0,
#3480
0'
#3486
b1001011 @
1'
#3487
1,
#3492
0'
#3498
b1001010 @
1'
0,
#3504
0'
#3509
1,
#3510
b1001001 @
1'
#3516
0'
#3520
0,
#3522
b1001000 @
1'
#3528
0'
#3531
1,
#3534
b1000111 @
1'
#3540
0'
#3542
0,
#3546
b1000110 @
1'
#3552
0'
#3553
1,
#3558
b1000101 @
1'
#3564
0'
0,
#3570
b1000100 @
1'
#3575
1,
#3576
0'
#3582
b1000011 @
1'
#3586
0,
#3588
0'
#3594
b1000010 @
1'
#3597
1,
#3600
0'
#3606
b1000001 @
1'
#3608
0,
#3612
0'
#3618
b1000000 @
1'
#3619
1,
#3624
0'
#3630
b111111 @
1'
0,
#3636
0'
#3641
1,
#3642
b111110 @
1'
#3648
0'
#3652
0,
#3654
b111101 @
1'
#3660
0'
#3663
1,
#3666
b111100 @
1'
#3672
0'
#3674
0,
#3678
b111011 @
1'
#3684
0'
#3685
1,
#3690
b111010 @
1'
#3696
0'
0,
#3702
b111001 @
1'
#3707
1,
#3708
0'
#3714
b111000 @
1'
